Workbook

Sheet Despiece
A2: Baño Cartagena · despiece independiente
A3: Fuente: fotos IMG_4304–4307 y medidas del usuario, 27/10/2026. Mismo RH15 de cocina y clóset; compra conjunta en compras-proyecto.xlsx.
A4: Medidas terminadas en mm. Largo en sentido de veta. B06 se pide rectangular entero; la diagonal, el sifón y los equipos se mecanizan con plantilla confirmada.
A6: ID | B6: Módulo | C6: Pieza | D6: Material | E6: Cantidad | F6: Largo veta mm | G6: Ancho mm | H6: Espesor mm | I6: Área m² | J6: Canto L1 | K6: Canto L2 | L6: Canto A1 | M6: Canto A2 | N6: Corte largo mm | O6: Corte ancho mm | P6: Nota de fabricación
A7: B01 | B7: BAJO | C7: Lateral | D7: RH15 Cartagena | E7: 2 | F7: 470 | G7: 450 | H7: 15 | I7: =E7*F7*G7/1000000 -> 0.423 | J7: 2 | K7: 0.45 | L7: 0.45 | M7: 0.45 | N7: =F7-IF(L7="2",2,IF(L7="0.45",0.45,0))-IF(M7="2",2,IF(M7="0.45",0.45,0)) -> 469.1 | O7: =G7-IF(J7="2",2,IF(J7="0.45",0.45,0))-IF(K7="2",2,IF(K7="0.45",0.45,0)) -> 447.55 | P7: Zona húmeda: proteger todos los bordes y sellar perforaciones; dimensiones terminadas.
A8: B02 | B8: BAJO | C8: Piso | D8: RH15 Cartagena | E8: 1 | F8: 490 | G8: 450 | H8: 15 | I8: =E8*F8*G8/1000000 -> 0.2205 | J8: 2 | K8: 0.45 | L8: 0.45 | M8: 0.45 | N8: =F8-IF(L8="2",2,IF(L8="0.45",0.45,0))-IF(M8="2",2,IF(M8="0.45",0.45,0)) -> 489.1 | O8: =G8-IF(J8="2",2,IF(J8="0.45",0.45,0))-IF(K8="2",2,IF(K8="0.45",0.45,0)) -> 447.55 | P8: Zona húmeda: proteger todos los bordes y sellar perforaciones; dimensiones terminadas.
A9: B03 | B9: BAJO | C9: Entrepaño retranqueado con reserva de sifón | D9: RH15 Cartagena | E9: 1 | F9: 490 | G9: 405 | H9: 15 | I9: =E9*F9*G9/1000000 -> 0.19845 | J9: 2 | K9: 0.45 | L9: 0.45 | M9: 0.45 | N9: =F9-IF(L9="2",2,IF(L9="0.45",0.45,0))-IF(M9="2",2,IF(M9="0.45",0.45,0)) -> 489.1 | O9: =G9-IF(J9="2",2,IF(J9="0.45",0.45,0))-IF(K9="2",2,IF(K9="0.45",0.45,0)) -> 402.55 | P9: Zona húmeda: proteger todos los bordes y sellar perforaciones; dimensiones terminadas. Nicho libre de 150 mm bajo granito. Recorte trasero ilustrativo 100 × 270 mm, centrado; no mecanizar sin sifón real. Retranqueo frontal de 30 mm para agarre.
A10: B04 | B10: BAJO | C10: Travesaño trasero superior lateral | D10: RH15 Cartagena | E10: 2 | F10: 195 | G10: 80 | H10: 15 | I10: =E10*F10*G10/1000000 -> 0.0312 | J10: 0.45 | K10: 0.45 | L10: 0.45 | M10: 0.45 | N10: =F10-IF(L10="2",2,IF(L10="0.45",0.45,0))-IF(M10="2",2,IF(M10="0.45",0.45,0)) -> 194.1 | O10: =G10-IF(J10="2",2,IF(J10="0.45",0.45,0))-IF(K10="2",2,IF(K10="0.45",0.45,0)) -> 79.1 | P10: Zona húmeda: proteger todos los bordes y sellar perforaciones; dimensiones terminadas. De canto, interrumpido en el centro para tuberías; no es un colgador certificado.
A11: B05 | B11: BAJO | C11: Travesaño trasero inferior | D11: RH15 Cartagena | E11: 1 | F11: 490 | G11: 80 | H11: 15 | I11: =E11*F11*G11/1000000 -> 0.0392 | J11: 0.45 | K11: 0.45 | L11: 0.45 | M11: 0.45 | N11: =F11-IF(L11="2",2,IF(L11="0.45",0.45,0))-IF(M11="2",2,IF(M11="0.45",0.45,0)) -> 489.1 | O11: =G11-IF(J11="2",2,IF(J11="0.45",0.45,0))-IF(K11="2",2,IF(K11="0.45",0.45,0)) -> 79.1 | P11: Zona húmeda: proteger todos los bordes y sellar perforaciones; dimensiones terminadas. Define rigidez posterior; anclajes y uniones por dimensionar.
A12: B06 | B12: BAJO | C12: Panel común para dos puertas: corte diagonal en armado | D12: RH15 Cartagena | E12: 1 | F12: 299 | G12: 517 | H12: 15 | I12: =E12*F12*G12/1000000 -> 0.154583 | J12: 2 | K12: 2 | L12: 2 | M12: 2 | N12: =F12-IF(L12="2",2,IF(L12="0.45",0.45,0))-IF(M12="2",2,IF(M12="0.45",0.45,0)) -> 295 | O12: =G12-IF(J12="2",2,IF(J12="0.45",0.45,0))-IF(K12="2",2,IF(K12="0.45",0.45,0)) -> 513 | P12: Una sola pieza rectangular terminada 517 × 299 mm (veta vertical). Pedirla entera, con canto 2 mm en el perímetro; NO dividir en tienda. En el armado, corte central a 75° de la horizontal (provisional entre 70 y 80°) con el disco Diablo de 1,5 mm (corte de 0,059") y canto flexible 0,45 mm en los dos bordes nuevos. Holgura entre puertas tras cantear ≈0,6 mm: probablemente insuficiente (ver Pendientes). La medida de lista es del panel común, no de cada tapa.
A13: S01 | B13: ESPEJO | C13: Lateral gabinete superior | D13: RH15 Cartagena | E13: 2 | F13: 500 | G13: 105 | H13: 15 | I13: =E13*F13*G13/1000000 -> 0.105 | J13: 2 | K13: 0.45 | L13: 0.45 | M13: 0.45 | N13: =F13-IF(L13="2",2,IF(L13="0.45",0.45,0))-IF(M13="2",2,IF(M13="0.45",0.45,0)) -> 499.1 | O13: =G13-IF(J13="2",2,IF(J13="0.45",0.45,0))-IF(K13="2",2,IF(K13="0.45",0.45,0)) -> 102.55 | P13: Zona húmeda: proteger todos los bordes y sellar perforaciones; dimensiones terminadas. Fondo total 130 mm con panel 6 mm, holgura frontal 1 mm, tapa RH15 y espejo 3 mm.
A14: S02 | B14: ESPEJO | C14: Piso y techo gabinete superior | D14: RH15 Cartagena | E14: 2 | F14: 420 | G14: 105 | H14: 15 | I14: =E14*F14*G14/1000000 -> 0.0882 | J14: 2 | K14: 0.45 | L14: 0.45 | M14: 0.45 | N14: =F14-IF(L14="2",2,IF(L14="0.45",0.45,0))-IF(M14="2",2,IF(M14="0.45",0.45,0)) -> 419.1 | O14: =G14-IF(J14="2",2,IF(J14="0.45",0.45,0))-IF(K14="2",2,IF(K14="0.45",0.45,0)) -> 102.55 | P14: Zona húmeda: proteger todos los bordes y sellar perforaciones; dimensiones terminadas.
A15: S03 | B15: ESPEJO | C15: División vertical | D15: RH15 Cartagena | E15: 1 | F15: 470 | G15: 105 | H15: 15 | I15: =E15*F15*G15/1000000 -> 0.04935 | J15: 2 | K15: 0.45 | L15: 0.45 | M15: 0.45 | N15: =F15-IF(L15="2",2,IF(L15="0.45",0.45,0))-IF(M15="2",2,IF(M15="0.45",0.45,0)) -> 469.1 | O15: =G15-IF(J15="2",2,IF(J15="0.45",0.45,0))-IF(K15="2",2,IF(K15="0.45",0.45,0)) -> 102.55 | P15: Zona húmeda: proteger todos los bordes y sellar perforaciones; dimensiones terminadas. Interior cerrado 290 mm; columna derecha abierta 115 mm.
A16: S04 | B16: ESPEJO | C16: Entrepaño interior izquierdo | D16: RH15 Cartagena | E16: 2 | F16: 290 | G16: 100 | H16: 15 | I16: =E16*F16*G16/1000000 -> 0.058 | J16: 2 | K16: 0.45 | L16: 0.45 | M16: 0.45 | N16: =F16-IF(L16="2",2,IF(L16="0.45",0.45,0))-IF(M16="2",2,IF(M16="0.45",0.45,0)) -> 289.1 | O16: =G16-IF(J16="2",2,IF(J16="0.45",0.45,0))-IF(K16="2",2,IF(K16="0.45",0.45,0)) -> 97.55 | P16: Zona húmeda: proteger todos los bordes y sellar perforaciones; dimensiones terminadas. Dos entrepaños fijos como la referencia.
A17: S05 | B17: ESPEJO | C17: Entrepaño columna abierta derecha | D17: RH15 Cartagena | E17: 1 | F17: 115 | G17: 100 | H17: 15 | I17: =E17*F17*G17/1000000 -> 0.0115 | J17: 2 | K17: 0.45 | L17: 0.45 | M17: 0.45 | N17: =F17-IF(L17="2",2,IF(L17="0.45",0.45,0))-IF(M17="2",2,IF(M17="0.45",0.45,0)) -> 114.1 | O17: =G17-IF(J17="2",2,IF(J17="0.45",0.45,0))-IF(K17="2",2,IF(K17="0.45",0.45,0)) -> 97.55 | P17: Zona húmeda: proteger todos los bordes y sellar perforaciones; dimensiones terminadas.
A18: S06 | B18: ESPEJO | C18: Tapa RH15 portadora del espejo | D18: RH15 Cartagena | E18: 1 | F18: 500 | G18: 320 | H18: 15 | I18: =E18*F18*G18/1000000 -> 0.16 | J18: 2 | K18: 2 | L18: 2 | M18: 2 | N18: =F18-IF(L18="2",2,IF(L18="0.45",0.45,0))-IF(M18="2",2,IF(M18="0.45",0.45,0)) -> 496 | O18: =G18-IF(J18="2",2,IF(J18="0.45",0.45,0))-IF(K18="2",2,IF(K18="0.45",0.45,0)) -> 316 | P18: Medida exterior de referencia 320 × 500; espejo pegado en cara exterior. Dos bisagras candidatas, peso conjunto aproximado 2,8 kg sin herrajes. Validar holguras, cazoletas y adhesivo compatible con espejo.
... A21: E02 | B21: BAJO | C21: Granito de retal | D21: Granito de retal provisional | E21: 1 | F21: 550 | G21: 470 | H21: 20 | I21: =E21*F21*G21/1000000 -> 0.2585 | J21: — | K21: — | L21: — | M21: — | N21: =F21-IF(L21="2",2,IF(L21="0.45",0.45,0))-IF(M21="2",2,IF(M21="0.45",0.45,0)) -> 550 | O21: =G21-IF(J21="2",2,IF(J21="0.45",0.45,0))-IF(K21="2",2,IF(K21="0.45",0.45,0)) -> 470 | P21: 550 × 470 × 20 mm supuestos. Vuelos laterales 15 mm; delante 5 mm respecto a las puertas. Recortes solo con lavamanos, grifería y retal reales.
A24: Total RH15 (sin espejo, granito ni fondo) | E24: =SUMIF(D7:D21,"RH15 Cartagena",E7:E21) -> 17 | I24: =SUMIF(D7:D21,"RH15 Cartagena",I7:I21) -> 1.538983
A25: Fondo blanco RH6, sin asignar sobrantes | E25: =SUMIF(D7:D21,"Fondo melamina blanco RH6",E7:E21) -> 1 | I25: =SUMIF(D7:D21,"Fondo melamina blanco RH6",I7:I21) -> 0.221216

Sheet Pedido de corte
A2: Pedido de corte y canteado · baño | P2: ¿El proveedor descuenta cantos de la medida terminada? | Q2: SÍ
A3: Pedir únicamente los bordes indicados. Diagonal de B06 y recortes de obra pendientes; el proveedor confirma tolerancias y cabida en máquina. | P3: Lado menor mínimo del tablero para máquina, mm | Q3: 100
A4: SÍ = medida terminada; NO = tablero con descuento. Se clasifica con el tamaño del tablero. B06: pedir un único panel 517 × 299 terminado; NO separar en tienda. Diagonal central provisional 75° en armado. | P4: Lado mayor mínimo del tablero para máquina, mm | Q4: 250
A6: ID | B6: Módulo | C6: Pieza | D6: Material | E6: Cantidad | F6: Largo a pedir | G6: Ancho a pedir | H6: Largo 1 | I6: Largo 2 | J6: Corto 1 | K6: Corto 2 | L6: Canteo | M6: Medida terminada | N6: Observación
A7: =Despiece!A7 -> B01 | B7: =Despiece!B7 -> BAJO | C7: =Despiece!C7 -> Lateral | D7: =Despiece!D7 -> RH15 Cartagena | E7: =Despiece!E7 -> 2 | F7: =IF($Q$2="NO",ROUND(Despiece!N7,2),Despiece!F7) -> 470 | G7: =IF($Q$2="NO",ROUND(Despiece!O7,2),Despiece!G7) -> 450 | H7: =IF(Despiece!J7="2","R",IF(Despiece!J7="0.45","F","—")) -> R | I7: =IF(Despiece!K7="2","R",IF(Despiece!K7="0.45","F","—")) -> F | J7: =IF(Despiece!L7="2","R",IF(Despiece!L7="0.45","F","—")) -> F | K7: =IF(Despiece!M7="2","R",IF(Despiece!M7="0.45","F","—")) -> F | L7: =IF(SUMPRODUCT((Despiece!J7:M7="2")+(Despiece!J7:M7="0.45"))=0,"Sin canto",IF(OR(MIN(Despiece!N7,Despiece!O7)<$Q$3,MAX(Despiece!N7,Despiece!O7)<$Q$4),"Pequeña","Normal")) -> Normal | M7: =Despiece!F7&" × "&Despiece!G7 -> 470 × 450 | N7: =IF(L7="Pequeña","Si no la cantean: cortar a "&ROUND(Despiece!N7,2)&" × "&ROUND(Despiece!O7,2)&" y cantear en taller. ","")&Despiece!P7 -> Zona húmeda: proteger todos los bordes y sellar perforaciones; dimensiones terminadas.
A8: =Despiece!A8 -> B02 | B8: =Despiece!B8 -> BAJO | C8: =Despiece!C8 -> Piso | D8: =Despiece!D8 -> RH15 Cartagena | E8: =Despiece!E8 -> 1 | F8: =IF($Q$2="NO",ROUND(Despiece!N8,2),Despiece!F8) -> 490 | G8: =IF($Q$2="NO",ROUND(Despiece!O8,2),Despiece!G8) -> 450 | H8: =IF(Despiece!J8="2","R",IF(Despiece!J8="0.45","F","—")) -> R | I8: =IF(Despiece!K8="2","R",IF(Despiece!K8="0.45","F","—")) -> F | J8: =IF(Despiece!L8="2","R",IF(Despiece!L8="0.45","F","—")) -> F | K8: =IF(Despiece!M8="2","R",IF(Despiece!M8="0.45","F","—")) -> F | L8: =IF(SUMPRODUCT((Despiece!J8:M8="2")+(Despiece!J8:M8="0.45"))=0,"Sin canto",IF(OR(MIN(Despiece!N8,Despiece!O8)<$Q$3,MAX(Despiece!N8,Despiece!O8)<$Q$4),"Pequeña","Normal")) -> Normal | M8: =Despiece!F8&" × "&Despiece!G8 -> 490 × 450 | N8: =IF(L8="Pequeña","Si no la cantean: cortar a "&ROUND(Despiece!N8,2)&" × "&ROUND(Despiece!O8,2)&" y cantear en taller. ","")&Despiece!P8 -> Zona húmeda: proteger todos los bordes y sellar perforaciones; dimensiones terminadas.
A9: =Despiece!A9 -> B03 | B9: =Despiece!B9 -> BAJO | C9: =Despiece!C9 -> Entrepaño retranqueado con reserva de sifón | D9: =Despiece!D9 -> RH15 Cartagena | E9: =Despiece!E9 -> 1 | F9: =IF($Q$2="NO",ROUND(Despiece!N9,2),Despiece!F9) -> 490 | G9: =IF($Q$2="NO",ROUND(Despiece!O9,2),Despiece!G9) -> 405 | H9: =IF(Despiece!J9="2","R",IF(Despiece!J9="0.45","F","—")) -> R | I9: =IF(Despiece!K9="2","R",IF(Despiece!K9="0.45","F","—")) -> F | J9: =IF(Despiece!L9="2","R",IF(Despiece!L9="0.45","F","—")) -> F | K9: =IF(Despiece!M9="2","R",IF(Despiece!M9="0.45","F","—")) -> F | L9: =IF(SUMPRODUCT((Despiece!J9:M9="2")+(Despiece!J9:M9="0.45"))=0,"Sin canto",IF(OR(MIN(Despiece!N9,Despiece!O9)<$Q$3,MAX(Despiece!N9,Despiece!O9)<$Q$4),"Pequeña","Normal")) -> Normal | M9: =Despiece!F9&" × "&Despiece!G9 -> 490 × 405 | N9: =IF(L9="Pequeña","Si no la cantean: cortar a "&ROUND(Despiece!N9,2)&" × "&ROUND(Despiece!O9,2)&" y cantear en taller. ","")&Despiece!P9 -> Zona húmeda: proteger todos los bordes y sellar perforaciones; dimensiones terminadas. Nicho libre de 150 mm bajo granito. Recorte trasero ilustrativo 100 × 270 mm, centrado; no mecanizar sin sifón real. Retranqueo frontal de 30 mm para agarre.
A10: =Despiece!A10 -> B04 | B10: =Despiece!B10 -> BAJO | C10: =Despiece!C10 -> Travesaño trasero superior lateral | D10: =Despiece!D10 -> RH15 Cartagena | E10: =Despiece!E10 -> 2 | F10: =IF($Q$2="NO",ROUND(Despiece!N10,2),Despiece!F10) -> 195 | G10: =IF($Q$2="NO",ROUND(Despiece!O10,2),Despiece!G10) -> 80 | H10: =IF(Despiece!J10="2","R",IF(Despiece!J10="0.45","F","—")) -> F | I10: =IF(Despiece!K10="2","R",IF(Despiece!K10="0.45","F","—")) -> F | J10: =IF(Despiece!L10="2","R",IF(Despiece!L10="0.45","F","—")) -> F | K10: =IF(Despiece!M10="2","R",IF(Despiece!M10="0.45","F","—")) -> F | L10: =IF(SUMPRODUCT((Despiece!J10:M10="2")+(Despiece!J10:M10="0.45"))=0,"Sin canto",IF(OR(MIN(Despiece!N10,Despiece!O10)<$Q$3,MAX(Despiece!N10,Despiece!O10)<$Q$4),"Pequeña","Normal")) -> Pequeña | M10: =Despiece!F10&" × "&Despiece!G10 -> 195 × 80 | N10: =IF(L10="Pequeña","Si no la cantean: cortar a "&ROUND(Despiece!N10,2)&" × "&ROUND(Despiece!O10,2)&" y cantear en taller. ","")&Despiece!P10 -> Si no la cantean: cortar a 194,1 × 79,1 y cantear en taller. Zona húmeda: proteger todos los bordes y sellar perforaciones; dimensiones terminadas. De canto, interrumpido en el centro para tuberías; no es un colgador certificado.
A11: =Despiece!A11 -> B05 | B11: =Despiece!B11 -> BAJO | C11: =Despiece!C11 -> Travesaño trasero inferior | D11: =Despiece!D11 -> RH15 Cartagena | E11: =Despiece!E11 -> 1 | F11: =IF($Q$2="NO",ROUND(Despiece!N11,2),Despiece!F11) -> 490 | G11: =IF($Q$2="NO",ROUND(Despiece!O11,2),Despiece!G11) -> 80 | H11: =IF(Despiece!J11="2","R",IF(Despiece!J11="0.45","F","—")) -> F | I11: =IF(Despiece!K11="2","R",IF(Despiece!K11="0.45","F","—")) -> F | J11: =IF(Despiece!L11="2","R",IF(Despiece!L11="0.45","F","—")) -> F | K11: =IF(Despiece!M11="2","R",IF(Despiece!M11="0.45","F","—")) -> F | L11: =IF(SUMPRODUCT((Despiece!J11:M11="2")+(Despiece!J11:M11="0.45"))=0,"Sin canto",IF(OR(MIN(Despiece!N11,Despiece!O11)<$Q$3,MAX(Despiece!N11,Despiece!O11)<$Q$4),"Pequeña","Normal")) -> Pequeña | M11: =Despiece!F11&" × "&Despiece!G11 -> 490 × 80 | N11: =IF(L11="Pequeña","Si no la cantean: cortar a "&ROUND(Despiece!N11,2)&" × "&ROUND(Despiece!O11,2)&" y cantear en taller. ","")&Despiece!P11 -> Si no la cantean: cortar a 489,1 × 79,1 y cantear en taller. Zona húmeda: proteger todos los bordes y sellar perforaciones; dimensiones terminadas. Define rigidez posterior; anclajes y uniones por dimensionar.
A12: =Despiece!A12 -> B06 | B12: =Despiece!B12 -> BAJO | C12: =Despiece!C12 -> Panel común para dos puertas: corte diagonal en armado | D12: =Despiece!D12 -> RH15 Cartagena | E12: =Despiece!E12 -> 1 | F12: =IF($Q$2="NO",ROUND(Despiece!N12,2),Despiece!F12) -> 299 | G12: =IF($Q$2="NO",ROUND(Despiece!O12,2),Despiece!G12) -> 517 | H12: =IF(Despiece!J12="2","R",IF(Despiece!J12="0.45","F","—")) -> R | I12: =IF(Despiece!K12="2","R",IF(Despiece!K12="0.45","F","—")) -> R | J12: =IF(Despiece!L12="2","R",IF(Despiece!L12="0.45","F","—")) -> R | K12: =IF(Despiece!M12="2","R",IF(Despiece!M12="0.45","F","—")) -> R | L12: =IF(SUMPRODUCT((Despiece!J12:M12="2")+(Despiece!J12:M12="0.45"))=0,"Sin canto",IF(OR(MIN(Despiece!N12,Despiece!O12)<$Q$3,MAX(Despiece!N12,Despiece!O12)<$Q$4),"Pequeña","Normal")) -> Normal | M12: =Despiece!F12&" × "&Despiece!G12 -> 299 × 517 | N12: =IF(L12="Pequeña","Si no la cantean: cortar a "&ROUND(Despiece!N12,2)&" × "&ROUND(Despiece!O12,2)&" y cantear en taller. ","")&Despiece!P12 -> Una sola pieza rectangular terminada 517 × 299 mm (veta vertical). Pedirla entera, con canto 2 mm en el perímetro; NO dividir en tienda. En el armado, corte central a 75° de la horizontal (provisional entre 70 y 80°) con el disco Diablo de 1,5 mm (corte de 0,059") y canto flexible 0,45 mm en los dos bordes nuevos. Holgura entre puertas tras cantear ≈0,6 mm: probablemente insuficiente (ver Pendientes). La medida de lista es del panel común, no de cada tapa.
A13: =Despiece!A13 -> S01 | B13: =Despiece!B13 -> ESPEJO | C13: =Despiece!C13 -> Lateral gabinete superior | D13: =Despiece!D13 -> RH15 Cartagena | E13: =Despiece!E13 -> 2 | F13: =IF($Q$2="NO",ROUND(Despiece!N13,2),Despiece!F13) -> 500 | G13: =IF($Q$2="NO",ROUND(Despiece!O13,2),Despiece!G13) -> 105 | H13: =IF(Despiece!J13="2","R",IF(Despiece!J13="0.45","F","—")) -> R | I13: =IF(Despiece!K13="2","R",IF(Despiece!K13="0.45","F","—")) -> F | J13: =IF(Despiece!L13="2","R",IF(Despiece!L13="0.45","F","—")) -> F | K13: =IF(Despiece!M13="2","R",IF(Despiece!M13="0.45","F","—")) -> F | L13: =IF(SUMPRODUCT((Despiece!J13:M13="2")+(Despiece!J13:M13="0.45"))=0,"Sin canto",IF(OR(MIN(Despiece!N13,Despiece!O13)<$Q$3,MAX(Despiece!N13,Despiece!O13)<$Q$4),"Pequeña","Normal")) -> Normal | M13: =Despiece!F13&" × "&Despiece!G13 -> 500 × 105 | N13: =IF(L13="Pequeña","Si no la cantean: cortar a "&ROUND(Despiece!N13,2)&" × "&ROUND(Despiece!O13,2)&" y cantear en taller. ","")&Despiece!P13 -> Zona húmeda: proteger todos los bordes y sellar perforaciones; dimensiones terminadas. Fondo total 130 mm con panel 6 mm, holgura frontal 1 mm, tapa RH15 y espejo 3 mm.
A14: =Despiece!A14 -> S02 | B14: =Despiece!B14 -> ESPEJO | C14: =Despiece!C14 -> Piso y techo gabinete superior | D14: =Despiece!D14 -> RH15 Cartagena | E14: =Despiece!E14 -> 2 | F14: =IF($Q$2="NO",ROUND(Despiece!N14,2),Despiece!F14) -> 420 | G14: =IF($Q$2="NO",ROUND(Despiece!O14,2),Despiece!G14) -> 105 | H14: =IF(Despiece!J14="2","R",IF(Despiece!J14="0.45","F","—")) -> R | I14: =IF(Despiece!K14="2","R",IF(Despiece!K14="0.45","F","—")) -> F | J14: =IF(Despiece!L14="2","R",IF(Despiece!L14="0.45","F","—")) -> F | K14: =IF(Despiece!M14="2","R",IF(Despiece!M14="0.45","F","—")) -> F | L14: =IF(SUMPRODUCT((Despiece!J14:M14="2")+(Despiece!J14:M14="0.45"))=0,"Sin canto",IF(OR(MIN(Despiece!N14,Despiece!O14)<$Q$3,MAX(Despiece!N14,Despiece!O14)<$Q$4),"Pequeña","Normal")) -> Normal | M14: =Despiece!F14&" × "&Despiece!G14 -> 420 × 105 | N14: =IF(L14="Pequeña","Si no la cantean: cortar a "&ROUND(Despiece!N14,2)&" × "&ROUND(Despiece!O14,2)&" y cantear en taller. ","")&Despiece!P14 -> Zona húmeda: proteger todos los bordes y sellar perforaciones; dimensiones terminadas.
A15: =Despiece!A15 -> S03 | B15: =Despiece!B15 -> ESPEJO | C15: =Despiece!C15 -> División vertical | D15: =Despiece!D15 -> RH15 Cartagena | E15: =Despiece!E15 -> 1 | F15: =IF($Q$2="NO",ROUND(Despiece!N15,2),Despiece!F15) -> 470 | G15: =IF($Q$2="NO",ROUND(Despiece!O15,2),Despiece!G15) -> 105 | H15: =IF(Despiece!J15="2","R",IF(Despiece!J15="0.45","F","—")) -> R | I15: =IF(Despiece!K15="2","R",IF(Despiece!K15="0.45","F","—")) -> F | J15: =IF(Despiece!L15="2","R",IF(Despiece!L15="0.45","F","—")) -> F | K15: =IF(Despiece!M15="2","R",IF(Despiece!M15="0.45","F","—")) -> F | L15: =IF(SUMPRODUCT((Despiece!J15:M15="2")+(Despiece!J15:M15="0.45"))=0,"Sin canto",IF(OR(MIN(Despiece!N15,Despiece!O15)<$Q$3,MAX(Despiece!N15,Despiece!O15)<$Q$4),"Pequeña","Normal")) -> Normal | M15: =Despiece!F15&" × "&Despiece!G15 -> 470 × 105 | N15: =IF(L15="Pequeña","Si no la cantean: cortar a "&ROUND(Despiece!N15,2)&" × "&ROUND(Despiece!O15,2)&" y cantear en taller. ","")&Despiece!P15 -> Zona húmeda: proteger todos los bordes y sellar perforaciones; dimensiones terminadas. Interior cerrado 290 mm; columna derecha abierta 115 mm.
A16: =Despiece!A16 -> S04 | B16: =Despiece!B16 -> ESPEJO | C16: =Despiece!C16 -> Entrepaño interior izquierdo | D16: =Despiece!D16 -> RH15 Cartagena | E16: =Despiece!E16 -> 2 | F16: =IF($Q$2="NO",ROUND(Despiece!N16,2),Despiece!F16) -> 290 | G16: =IF($Q$2="NO",ROUND(Despiece!O16,2),Despiece!G16) -> 100 | H16: =IF(Despiece!J16="2","R",IF(Despiece!J16="0.45","F","—")) -> R | I16: =IF(Despiece!K16="2","R",IF(Despiece!K16="0.45","F","—")) -> F | J16: =IF(Despiece!L16="2","R",IF(Despiece!L16="0.45","F","—")) -> F | K16: =IF(Despiece!M16="2","R",IF(Despiece!M16="0.45","F","—")) -> F | L16: =IF(SUMPRODUCT((Despiece!J16:M16="2")+(Despiece!J16:M16="0.45"))=0,"Sin canto",IF(OR(MIN(Despiece!N16,Despiece!O16)<$Q$3,MAX(Despiece!N16,Despiece!O16)<$Q$4),"Pequeña","Normal")) -> Pequeña | M16: =Despiece!F16&" × "&Despiece!G16 -> 290 × 100 | N16: =IF(L16="Pequeña","Si no la cantean: cortar a "&ROUND(Despiece!N16,2)&" × "&ROUND(Despiece!O16,2)&" y cantear en taller. ","")&Despiece!P16 -> Si no la cantean: cortar a 289,1 × 97,55 y cantear en taller. Zona húmeda: proteger todos los bordes y sellar perforaciones; dimensiones terminadas. Dos entrepaños fijos como la referencia.
A17: =Despiece!A17 -> S05 | B17: =Despiece!B17 -> ESPEJO | C17: =Despiece!C17 -> Entrepaño columna abierta derecha | D17: =Despiece!D17 -> RH15 Cartagena | E17: =Despiece!E17 -> 1 | F17: =IF($Q$2="NO",ROUND(Despiece!N17,2),Despiece!F17) -> 115 | G17: =IF($Q$2="NO",ROUND(Despiece!O17,2),Despiece!G17) -> 100 | H17: =IF(Despiece!J17="2","R",IF(Despiece!J17="0.45","F","—")) -> R | I17: =IF(Despiece!K17="2","R",IF(Despiece!K17="0.45","F","—")) -> F | J17: =IF(Despiece!L17="2","R",IF(Despiece!L17="0.45","F","—")) -> F | K17: =IF(Despiece!M17="2","R",IF(Despiece!M17="0.45","F","—")) -> F | L17: =IF(SUMPRODUCT((Despiece!J17:M17="2")+(Despiece!J17:M17="0.45"))=0,"Sin canto",IF(OR(MIN(Despiece!N17,Despiece!O17)<$Q$3,MAX(Despiece!N17,Despiece!O17)<$Q$4),"Pequeña","Normal")) -> Pequeña | M17: =Despiece!F17&" × "&Despiece!G17 -> 115 × 100 | N17: =IF(L17="Pequeña","Si no la cantean: cortar a "&ROUND(Despiece!N17,2)&" × "&ROUND(Despiece!O17,2)&" y cantear en taller. ","")&Despiece!P17 -> Si no la cantean: cortar a 114,1 × 97,55 y cantear en taller. Zona húmeda: proteger todos los bordes y sellar perforaciones; dimensiones terminadas.
A18: =Despiece!A18 -> S06 | B18: =Despiece!B18 -> ESPEJO | C18: =Despiece!C18 -> Tapa RH15 portadora del espejo | D18: =Despiece!D18 -> RH15 Cartagena | E18: =Despiece!E18 -> 1 | F18: =IF($Q$2="NO",ROUND(Despiece!N18,2),Despiece!F18) -> 500 | G18: =IF($Q$2="NO",ROUND(Despiece!O18,2),Despiece!G18) -> 320 | H18: =IF(Despiece!J18="2","R",IF(Despiece!J18="0.45","F","—")) -> R | I18: =IF(Despiece!K18="2","R",IF(Despiece!K18="0.45","F","—")) -> R | J18: =IF(Despiece!L18="2","R",IF(Despiece!L18="0.45","F","—")) -> R | K18: =IF(Despiece!M18="2","R",IF(Despiece!M18="0.45","F","—")) -> R | L18: =IF(SUMPRODUCT((Despiece!J18:M18="2")+(Despiece!J18:M18="0.45"))=0,"Sin canto",IF(OR(MIN(Despiece!N18,Despiece!O18)<$Q$3,MAX(Despiece!N18,Despiece!O18)<$Q$4),"Pequeña","Normal")) -> Normal | M18: =Despiece!F18&" × "&Despiece!G18 -> 500 × 320 | N18: =IF(L18="Pequeña","Si no la cantean: cortar a "&ROUND(Despiece!N18,2)&" × "&ROUND(Despiece!O18,2)&" y cantear en taller. ","")&Despiece!P18 -> Medida exterior de referencia 320 × 500; espejo pegado en cara exterior. Dos bisagras candidatas, peso conjunto aproximado 2,8 kg sin herrajes. Validar holguras, cazoletas y adhesivo compatible con espejo.
A19: =Despiece!A19 -> F01 | B19: =Despiece!B19 -> ESPEJO | C19: =Despiece!C19 -> Fondo blanco de 6 mm | D19: =Despiece!D19 -> Fondo melamina blanco RH6 | E19: =Despiece!E19 -> 1 | F19: =IF($Q$2="NO",ROUND(Despiece!N19,2),Despiece!F19) -> 496 | G19: =IF($Q$2="NO",ROUND(Despiece!O19,2),Despiece!G19) -> 446 | H19: =IF(Despiece!J19="2","R",IF(Despiece!J19="0.45","F","—")) -> F | I19: =IF(Despiece!K19="2","R",IF(Despiece!K19="0.45","F","—")) -> F | J19: =IF(Despiece!L19="2","R",IF(Despiece!L19="0.45","F","—")) -> F | K19: =IF(Despiece!M19="2","R",IF(Despiece!M19="0.45","F","—")) -> F | L19: =IF(SUMPRODUCT((Despiece!J19:M19="2")+(Despiece!J19:M19="0.45"))=0,"Sin canto",IF(OR(MIN(Despiece!N19,Despiece!O19)<$Q$3,MAX(Despiece!N19,Despiece!O19)<$Q$4),"Pequeña","Normal")) -> Normal | M19: =Despiece!F19&" × "&Despiece!G19 -> 496 × 446 | N19: =IF(L19="Pequeña","Si no la cantean: cortar a "&ROUND(Despiece!N19,2)&" × "&ROUND(Despiece!O19,2)&" y cantear en taller. ","")&Despiece!P19 -> Fondo aplicado por detrás, retranqueado 2 mm de los bordes. Reutilización de sobrantes de cocina solo se comprobará en la optimización conjunta final. No soporta el anclaje del gabinete.

Sheet Compras
A2: Compras y accesorios · baño
A3: Referencias del baño. Tablero, fondo, canto y bisagras se compran junto con cocina y clóset en compras-proyecto.xlsx; equipos, anclajes y servicios pendientes.
A6: Referencia | B6: Uso | C6: Cantidad | D6: Unidad | E6: Precio COP | F6: Subtotal COP | G6: Estado | H6: Detalle | I6: Fuente
A7: RH15 Cartagena | B7: Tablero del conjunto | C7: =Despiece!I24 -> 1.538983 | D7: m² | F7: =IF(COUNT(C7,E7)=2,C7*E7,"Por cotizar") -> Por cotizar | G7: En compra conjunta | H7: Área neta; se compra con cocina y clóset: las piezas RH15 de los tres muebles caben en 8 láminas (compras-proyecto.xlsx). | I7: Mismo material de cocina.
A8: Fondo blanco RH6 | B8: Gabinete espejo | C8: =Despiece!I25 -> 0.221216 | D8: m² | F8: =IF(COUNT(C8,E8)=2,C8*E8,"Por cotizar") -> Por cotizar | G8: En compra conjunta | H8: Cabe en la lámina de fondo de la cocina (compras-proyecto.xlsx). | I8: Solicitud del usuario.
A9: Canto rígido 2 mm | B9: Bordes indicados | C9: =Cantos!E7 -> 10 | D9: m | F9: =IF(COUNT(C9,E9)=2,C9*E9,"Por cotizar") -> Por cotizar | G9: En compra conjunta | H9: Rollo rígido de 100 m conjunto más metros sueltos (compras-proyecto.xlsx). | I9: Hoja Cantos.
A10: Canto flexible 0,45 | B10: Protección húmeda | C10: =Cantos!E8 -> 18 | D10: m | F10: =IF(COUNT(C10,E10)=2,C10*E10,"Por cotizar") -> Por cotizar | G10: En compra conjunta | H10: Rollo flexible de 200 m conjunto. Incluye fondo RH6 y los dos cantos diagonales de B06, hechos a mano. | I10: Hoja Cantos.
A11: HBM897-01 candidata | B11: Seis bisagras, tres pares | C11: 3 | D11: par | E11: 17750 | F11: =IF(COUNT(C11,E11)=2,C11*E11,"Por cotizar") -> 53250 | G11: En compra conjunta | H11: Dos por puerta; se compran con las de la cocina (15 pares en total). Validar peso, cabida, sobreposición y plantilla. | I11: Precio del presupuesto de cocina; no cotización actual.
A12: Espejo | B12: 320 × 500 × 3 mm provisional | C12: 1 | D12: pieza | F12: =IF(COUNT(C12,E12)=2,C12*E12,"Por cotizar") -> Por cotizar | G12: Por cotizar | H12: Cantos pulidos; espesor y adhesivo con vidriero. | I12: Medidas del usuario; espesor supuesto.
A13: Retal de granito | B13: 550 × 470 × 20 mm provisional | C13: 1 | D13: pieza | F13: =IF(COUNT(C13,E13)=2,C13*E13,"Por cotizar") -> Por cotizar | G13: Por elegir | H13: Vuelos 15 mm a los lados y 5 mm delante; recortes según equipos. | I13: Supuesto solicitado por usuario.
A14: Lavamanos de sobreponer | B14: Bowl Ø350 × 140 ilustrativo | C14: 1 | D14: unidad | F14: =IF(COUNT(C14,E14)=2,C14*E14,"Por cotizar") -> Por cotizar | G14: Por elegir | H14: No es un modelo comercial seleccionado. | I14: Representación provisional.
A15: Grifería | B15: Mezclador alto ilustrativo | C15: 1 | D15: unidad | F15: =IF(COUNT(C15,E15)=2,C15*E15,"Por cotizar") -> Por cotizar | G15: Por elegir | H15: Medir alcance y altura según lavamanos. | I15: Representación provisional.
A16: Desagüe y sifón | B16: Evacuación del lavamanos | C16: 1 | D16: juego | F16: =IF(COUNT(C16,E16)=2,C16*E16,"Por cotizar") -> Por cotizar | G16: Por elegir | H16: Recorte de entrepaño solo con sifón y tuberías reales. | I16: Instalación pendiente.
A17: Soportes de granito/mueble | B17: Soportes estructurales a muro | C17: 2 | D17: unidad | F17: =IF(COUNT(C17,E17)=2,C17*E17,"Por cotizar") -> Por cotizar | G17: Por dimensionar | H17: Capacidad, anclajes y sustrato real; no depende del fondo RH6. | I17: Montaje por definir.
A18: Fijaciones del espejo | B18: Anclajes gabinete superior | C18: 1 | D18: juego | F18: =IF(COUNT(C18,E18)=2,C18*E18,"Por cotizar") -> Por cotizar | G18: Por dimensionar | H18: Fijar por estructura o herrajes de colgar adecuados. | I18: Instalador.
A19: Sellado y adhesivo | B19: Diagonal, recortes y espejo | C19: 1 | D19: lote | F19: =IF(COUNT(C19,E19)=2,C19*E19,"Por cotizar") -> Por cotizar | G19: Por cotizar | H19: Productos compatibles con RH, canto, piedra y espejo según aplicación. | I19: Taller y vidriero.
A20: Corte y montaje | B20: Canteado, diagonal e instalación | C20: 1 | D20: servicio | F20: =IF(COUNT(C20,E20)=2,C20*E20,"Por cotizar") -> Por cotizar | G20: Por cotizar | H20: Incluye división diagonal de B06 y ajuste de tuberías. | I20: Proveedor.
A22: REFERENCIAS CON PRECIO | F22: =SUM(F7:F20) -> 53250 | H22: Subtotal parcial del baño. Tablero, fondo y canto se presupuestan en compras-proyecto.xlsx; faltan espejo, retal, equipos, fijaciones y servicios.

Sheet Cantos
A2: Cantos del baño · protección por humedad | H2: Reserva por borde m | I2: 0.05
A3: Cantos completos por zona húmeda: todos los bordes de RH15 y del fondo RH6, incluidos los ocultos en uniones. La diagonal entre puertas lleva flexible 0,45 en sus dos bordes; su metraje se incluye aquí como acabado manual. | H3: Ángulo de la diagonal, grados | I3: 75 | J3: Longitud de cada diagonal, mm | K3: =Despiece!F12/SIN(RADIANS(I3)) -> 309.54758
H4: Corte del disco, mm (Diablo Ultra Finish 7-1/4", 0,059") | I4: 1.5 | J4: Holgura normal resultante, mm | K4: =I4-2*I5 -> 0.6
H5: Canto de cada diagonal, mm | I5: 0.45 | J5: Holgura horizontal aproximada, mm | K5: =K4/SIN(RADIANS(I3)) -> 0.62116571
A6: Tipo | B6: Metros netos | C6: Bordes | D6: Reserva m | E6: Metros con reserva | F6: Manual neto estimado | G6: Bordes manuales | H6: Previsión manual m
A7: Rígido 2 mm | B7: =(SUMPRODUCT(Despiece!$E$7:$E$19,Despiece!$F$7:$F$19,(Despiece!$J$7:$J$19="2")+(Despiece!$K$7:$K$19="2"))+SUMPRODUCT(Despiece!$E$7:$E$19,Despiece!$G$7:$G$19,(Despiece!$L$7:$L$19="2")+(Despiece!$M$7:$M$19="2")))/1000 -> 8.197 | C7: =SUMPRODUCT(Despiece!$E$7:$E$19,(Despiece!$J$7:$J$19="2")+(Despiece!$K$7:$K$19="2")+(Despiece!$L$7:$L$19="2")+(Despiece!$M$7:$M$19="2")) -> 20 | D7: =C7*$I$2 -> 1 | E7: =ROUNDUP(B7+D7,0) -> 10 | F7: =(SUMPRODUCT(Despiece!$E$7:$E$19,Despiece!$F$7:$F$19,(Despiece!$J$7:$J$19="2")+(Despiece!$K$7:$K$19="2"),--('Pedido de corte'!$L$7:$L$19="Pequeña"))+SUMPRODUCT(Despiece!$E$7:$E$19,Despiece!$G$7:$G$19,(Despiece!$L$7:$L$19="2")+(Despiece!$M$7:$M$19="2"),--('Pedido de corte'!$L$7:$L$19="Pequeña")))/1000 -> 0.695 | G7: =SUMPRODUCT(Despiece!$E$7:$E$19,(Despiece!$J$7:$J$19="2")+(Despiece!$K$7:$K$19="2")+(Despiece!$L$7:$L$19="2")+(Despiece!$M$7:$M$19="2"),--('Pedido de corte'!$L$7:$L$19="Pequeña")) -> 3 | H7: =IF(G7=0,0,ROUNDUP((F7+G7*0.1)*1.2,0)) -> 2
A8: Flexible 0,45 mm | B8: =(SUMPRODUCT(Despiece!$E$7:$E$19,Despiece!$F$7:$F$19,(Despiece!$J$7:$J$19="0.45")+(Despiece!$K$7:$K$19="0.45"))+SUMPRODUCT(Despiece!$E$7:$E$19,Despiece!$G$7:$G$19,(Despiece!$L$7:$L$19="0.45")+(Despiece!$M$7:$M$19="0.45")))/1000+2*$K$3/1000 -> 14.828095 | C8: =SUMPRODUCT(Despiece!$E$7:$E$19,(Despiece!$J$7:$J$19="0.45")+(Despiece!$K$7:$K$19="0.45")+(Despiece!$L$7:$L$19="0.45")+(Despiece!$M$7:$M$19="0.45"))+2 -> 54 | D8: =C8*$I$2 -> 2.7 | E8: =ROUNDUP(B8+D8,0) -> 18 | F8: =(SUMPRODUCT(Despiece!$E$7:$E$19,Despiece!$F$7:$F$19,(Despiece!$J$7:$J$19="0.45")+(Despiece!$K$7:$K$19="0.45"),--('Pedido de corte'!$L$7:$L$19="Pequeña"))+SUMPRODUCT(Despiece!$E$7:$E$19,Despiece!$G$7:$G$19,(Despiece!$L$7:$L$19="0.45")+(Despiece!$M$7:$M$19="0.45"),--('Pedido de corte'!$L$7:$L$19="Pequeña")))/1000+2*$K$3/1000 -> 4.1540952 | G8: =SUMPRODUCT(Despiece!$E$7:$E$19,(Despiece!$J$7:$J$19="0.45")+(Despiece!$K$7:$K$19="0.45")+(Despiece!$L$7:$L$19="0.45")+(Despiece!$M$7:$M$19="0.45"),--('Pedido de corte'!$L$7:$L$19="Pequeña"))+2 -> 23 | H8: =IF(G8=0,0,ROUNDUP((F8+G8*0.1)*1.2,0)) -> 8
A10: Manual: piezas potencialmente rechazadas, más 10 cm por borde y 20 % de reserva. Confirmar entrega real antes de comprar.
A11: El canto se compra junto con cocina y clóset (compras-proyecto.xlsx): 1 rollo rígido de 100 m con metros sueltos y 1 rollo flexible de 200 m para los tres muebles.
A12: B06 se cuenta una vez como panel de suministro; sus dos bordes diagonales llevan flexible a mano. El metraje manual está incluido en el total, no se suma dos veces.

Sheet Pendientes
A2: Pendientes antes de cortar e instalar · baño
A3: Solo lo que falta resolver. Lo ya decidido está en la hoja Decisiones; el despiece y el 3D ya lo reflejan.
A6: N° | B6: Tema | C6: Qué falta | D6: Qué bloquea | E6: Quién lo define
A7: 1 | B7: Proveedor de corte | C7: Confirmar Q2–Q4 del Pedido de corte (medida terminada y tamaño mínimo que cantea). El pedido conjunto de los tres muebles está en compras-proyecto.xlsx. | D7: Pedido de corte | E7: Sucursal Madecentro
A8: 2 | B8: Granito y equipos | C8: Elegir el retal de granito (espesor real; se supusieron 2 cm), el lavamanos, la grifería y el desagüe. Los huecos del dibujo (Ø45 desagüe, Ø35 grifería) no son plantilla. | D8: Alturas de instalación y recortes del granito | E8: Usuario / marmolero
A9: 3 | B9: Alturas de instalación | C9: Confirmar la cara inferior del granito a 73 cm y los 51 cm desde su cara superior al gabinete (base a 126 y techo a 176 cm). | D9: Instalación | E9: Usuario
A10: 4 | B10: Diagonal de las puertas (B06) | C10: Pedir el panel entero, sin dividir en tienda. Con el disco Diablo de 1,5 mm la holgura entre puertas queda en ≈0,6 mm tras cantear; lo usual son 2–3 mm. Antes del corte diagonal, decidir si se da una segunda pasada o se lija cada borde hasta ~2 mm de holgura, y confirmar el ángulo (75° provisional). | D10: Corte diagonal en el armado | E10: Taller
A11: 5 | B11: Recorte del entrepaño | C11: Recortar y sellar en B03 la reserva del sifón con las piezas reales (100 × 270 ilustrativa). | D11: Armado | E11: Taller / plomero
A12: 6 | B12: Suspensión del mueble | C12: Dos soportes al muro resistente que carguen mueble, granito, agua y equipos: tipo de muro, herraje y tornillos. No colgar nada del fondo de 6 mm. | D12: Instalación | E12: Instalador
A13: 7 | B13: Gabinete del espejo | C13: Comprobar las bisagras HBM897-01 con la puerta de ≈2,8 kg (RH + espejo): capacidad, plantilla y poco fondo; fijar a la estructura. Espesor del espejo y adhesivo con el vidriero. | D13: Compra de bisagras y espejo | E13: Proveedor / vidriero
A14: 8 | B14: Ubicación en la terraza | C14: Comprobar holguras y apertura real en la pared del sanitario (x = 2,12 m, giro 90°). | D14: Instalación | E14: Medición en obra

Sheet Decisiones
A2: Decisiones aplicadas · baño
A3: Registro de lo ya resuelto; el despiece y el 3D ya lo reflejan.
A6: Tema | B6: Decisión | C6: Fecha / fuente
A7: Medidas inferiores | B7: Cuerpo de 52 cm de ancho, 47 de alto y 45 de fondo sin puertas; base a 26 cm del suelo. Las puertas añaden 15 mm al fondo. | C7: Medidas del usuario, 27/10/2026.
A8: Gabinete superior | B8: 45 × 50 × 13 cm totales. Tapa portadora de 32 × 50 en RH15 con espejo de 3 mm provisional; fondo blanco RH6. | C8: Medidas y fotos del usuario.
A9: Material | B9: RH15 Cartagena como cocina y clóset; fondo blanco RH6. | C9: Decisión del usuario.
A10: Cantos completos | B10: Zona húmeda: todos los bordes de RH15 y del fondo llevan canto, incluidos los ocultos en uniones; los dos bordes diagonales de B06 se cantean con flexible 0,45 en el armado; la muesca del sifón y las perforaciones se sellan. A diferencia de cocina y clóset, aquí no se retira el canto de los bordes ocultos. El RH no se trata como material impermeable. | C10: Decisión del usuario 27/10/2026.
A11: Compra conjunta | B11: Tablero, fondo, canto y bisagras se compran con cocina y clóset (compras-proyecto.xlsx): las piezas RH15 de los tres muebles caben en 8 láminas y el fondo del gabinete en la lámina de fondo de la cocina. | C11: Encaje conjunto del 27/10/2026.
A12: Ubicación | B12: Pared del sanitario, x = 2,12 m, giro 90°, con el extremo del granito en la esquina z = 2,20 m; ya no va en la pared de la puerta. | C12: Modelo general de la terraza.
A13: Disco para la diagonal de B06 | B13: Diablo Ultra Finish 7-1/4" con corte de 0,059" (≈1,5 mm). La holgura resultante (≈0,6 mm) queda como pendiente. | C13: Dato del usuario 27/10/2026
