Workbook

Sheet Despiece
A1: Despiece cocina terraza · melamina Cartagena RH 15 mm · fondos melamina blanco 6 mm · L = sentido de la veta
A2: E/F = dimensiones terminadas. B3 único de 750 sustituye B3+B4. Sin B0 ni S0; posiciones en Distribución.
A3: E/F terminadas; L/M corte antes de canto. Bases B3 aplicadas bajo las paredes: 693 × 550 × 15. Alturas de paredes reducidas 15 mm; detalle en Revisión.
A4: N° | B4: Módulo | C4: Pieza | D4: Material | E4: Largo veta terminado (mm) | F4: Ancho terminado (mm) | G4: Cant. | H4: Canto L1 | I4: Canto L2 | J4: Canto A1 | K4: Canto A2 | L4: Largo corte teórico (mm) | M4: Ancho corte teórico (mm)
A5: 03 | B5: B1 Basurero 30 | C5: Lateral | D5: Melamina Cartagena RH 15 | E5: 785 | F5: 580 | G5: 2 | H5: 2 | I5: 0.45 | J5: 0.45 | K5: 0.45 | L5: =E5-IF(J5="2",2,IF(J5="0.45",0.45,0))-IF(K5="2",2,IF(K5="0.45",0.45,0)) -> 784.1 | M5: =F5-IF(H5="2",2,IF(H5="0.45",0.45,0))-IF(I5="2",2,IF(I5="0.45",0.45,0)) -> 577.55
A6: 04 | B6: B1 Basurero 30 | C6: Piso | D6: Melamina Cartagena RH 15 | E6: 270 | F6: 580 | G6: 1 | H6: 2 | I6: 0.45 | J6: 0.45 | K6: 0.45 | L6: =E6-IF(J6="2",2,IF(J6="0.45",0.45,0))-IF(K6="2",2,IF(K6="0.45",0.45,0)) -> 269.1 | M6: =F6-IF(H6="2",2,IF(H6="0.45",0.45,0))-IF(I6="2",2,IF(I6="0.45",0.45,0)) -> 577.55
A7: 05 | B7: B1 Basurero 30 | C7: Travesaño (horizontales) | D7: Melamina Cartagena RH 15 | E7: 270 | F7: 100 | G7: 2 | H7: 0.45 | I7: 0.45 | J7: 0.45 | K7: 0.45 | L7: =E7-IF(J7="2",2,IF(J7="0.45",0.45,0))-IF(K7="2",2,IF(K7="0.45",0.45,0)) -> 269.1 | M7: =F7-IF(H7="2",2,IF(H7="0.45",0.45,0))-IF(I7="2",2,IF(I7="0.45",0.45,0)) -> 99.1
A8: 06 | B8: B1 Basurero 30 | C8: Fondo melamina 6 mm (clavado atrás) | D8: Fondo melamina 6 | E8: 296 | F8: 781 | G8: 1 | H8: — | I8: — | J8: — | K8: — | L8: =E8-IF(J8="2",2,IF(J8="0.45",0.45,0))-IF(K8="2",2,IF(K8="0.45",0.45,0)) -> 296 | M8: =F8-IF(H8="2",2,IF(H8="0.45",0.45,0))-IF(I8="2",2,IF(I8="0.45",0.45,0)) -> 781
A9: 07 | B9: B1 Basurero 30 | C9: Frente basurero | D9: Melamina Cartagena RH 15 | E9: 732 | F9: 297 | G9: 1 | H9: 2 | I9: 2 | J9: 2 | K9: 2 | L9: =E9-IF(J9="2",2,IF(J9="0.45",0.45,0))-IF(K9="2",2,IF(K9="0.45",0.45,0)) -> 728 | M9: =F9-IF(H9="2",2,IF(H9="0.45",0.45,0))-IF(I9="2",2,IF(I9="0.45",0.45,0)) -> 293
A10: 08 | B10: B2 Horno + estufa 60 | C10: Lateral | D10: Melamina Cartagena RH 15 | E10: 785 | F10: 580 | G10: 2 | H10: 2 | I10: 0.45 | J10: 0.45 | K10: 0.45 | L10: =E10-IF(J10="2",2,IF(J10="0.45",0.45,0))-IF(K10="2",2,IF(K10="0.45",0.45,0)) -> 784.1 | M10: =F10-IF(H10="2",2,IF(H10="0.45",0.45,0))-IF(I10="2",2,IF(I10="0.45",0.45,0)) -> 577.55
A11: 09 | B11: B2 Horno + estufa 60 | C11: Piso (apoyo horno) | D11: Melamina Cartagena RH 15 | E11: 570 | F11: 580 | G11: 1 | H11: 2 | I11: 0.45 | J11: 0.45 | K11: 0.45 | L11: =E11-IF(J11="2",2,IF(J11="0.45",0.45,0))-IF(K11="2",2,IF(K11="0.45",0.45,0)) -> 569.1 | M11: =F11-IF(H11="2",2,IF(H11="0.45",0.45,0))-IF(I11="2",2,IF(I11="0.45",0.45,0)) -> 577.55
A12: 10 | B12: B2 Horno + estufa 60 | C12: Repisa sobre horno | D12: Melamina Cartagena RH 15 | E12: 570 | F12: 500 | G12: 1 | H12: 2 | I12: 0.45 | J12: 0.45 | K12: 0.45 | L12: =E12-IF(J12="2",2,IF(J12="0.45",0.45,0))-IF(K12="2",2,IF(K12="0.45",0.45,0)) -> 569.1 | M12: =F12-IF(H12="2",2,IF(H12="0.45",0.45,0))-IF(I12="2",2,IF(I12="0.45",0.45,0)) -> 497.55
A13: 11 | B13: B2 Horno + estufa 60 | C13: Travesaño trasero | D13: Melamina Cartagena RH 15 | E13: 570 | F13: 100 | G13: 1 | H13: 0.45 | I13: 0.45 | J13: 0.45 | K13: 0.45 | L13: =E13-IF(J13="2",2,IF(J13="0.45",0.45,0))-IF(K13="2",2,IF(K13="0.45",0.45,0)) -> 569.1 | M13: =F13-IF(H13="2",2,IF(H13="0.45",0.45,0))-IF(I13="2",2,IF(I13="0.45",0.45,0)) -> 99.1
A14: 12 | B14: B2 Horno + estufa 60 | C14: Listón frontal de apoyo del mesón (de canto) | D14: Melamina Cartagena RH 15 | E14: 570 | F14: 80 | G14: 1 | H14: 0.45 | I14: 0.45 | J14: 0.45 | K14: 0.45 | L14: =E14-IF(J14="2",2,IF(J14="0.45",0.45,0))-IF(K14="2",2,IF(K14="0.45",0.45,0)) -> 569.1 | M14: =F14-IF(H14="2",2,IF(H14="0.45",0.45,0))-IF(I14="2",2,IF(I14="0.45",0.45,0)) -> 79.1
A15: 13 | B15: B2 Horno + estufa 60 | C15: Panel fijo bajo estufa (ajustar en obra) | D15: Melamina Cartagena RH 15 | E15: 145 | F15: 597 | G15: 1 | H15: 2 | I15: 2 | J15: 2 | K15: 2 | L15: =E15-IF(J15="2",2,IF(J15="0.45",0.45,0))-IF(K15="2",2,IF(K15="0.45",0.45,0)) -> 141 | M15: =F15-IF(H15="2",2,IF(H15="0.45",0.45,0))-IF(I15="2",2,IF(I15="0.45",0.45,0)) -> 593
A16: 14 | B16: B3 Cajonero único 75 | C16: Lateral | D16: Melamina Cartagena RH 15 | E16: 785 | F16: 580 | G16: 2 | H16: 2 | I16: 0.45 | J16: 0.45 | K16: 0.45 | L16: =E16-IF(J16="2",2,IF(J16="0.45",0.45,0))-IF(K16="2",2,IF(K16="0.45",0.45,0)) -> 784.1 | M16: =F16-IF(H16="2",2,IF(H16="0.45",0.45,0))-IF(I16="2",2,IF(I16="0.45",0.45,0)) -> 577.55
... A63: 77 | B63: S4 Platero 71,5 (herraje nominal 70) | C63: Fondo melamina 6 mm | D63: Fondo melamina 6 | E63: 711 | F63: 696 | G63: 1 | H63: — | I63: — | J63: — | K63: — | L63: =E63-IF(J63="2",2,IF(J63="0.45",0.45,0))-IF(K63="2",2,IF(K63="0.45",0.45,0)) -> 711 | M63: =F63-IF(H63="2",2,IF(H63="0.45",0.45,0))-IF(I63="2",2,IF(I63="0.45",0.45,0)) -> 696
C81: Total piezas melamina | G81: =SUMIF(D5:D79,"Melamina Cartagena RH 15",G5:G79) -> 75
C82: Total piezas de fondo 6 mm | G82: =SUMIF(D5:D79,"Fondo melamina 6",G5:G79) -> 7

Sheet Herrajes
A1: Herraje | B1: Cant. | C1: Uso
A2: Bisagra parche HBM897-01 · 35 mm · cierre lento (unidad física) | B2: 16 | C2: 16 unidades físicas = 8 pares comerciales. Dos por puerta; revisar carga antes de fabricar.
A3: Riel Bonuit HRE550-55N · negro · cierre lento 30 kg · 550 mm (par) | B3: 3 | C3: HRE550-55N negro, 550, cierre lento, lateral. Ficha aportada: 27 mm total confirmado (720−27=693), 13,5/lado para riel de 12,7. Alto 45 centrado en paredes 205/125/75: márgenes 80/40/15 mm. 30 kg, >25.000 ciclos; 3 pares incluyen 36 tornillos 4 × 12. Ancho máximo y carga útil aún por validar.
A4: Perfil gola superior × 3 m | B4: 1 | C4: Se usan unos 1,95 m: B1 300 + tramo B3–B5 1650; se interrumpe en el horno. Confirmar remates.
A5: Perfil gola media × 3 m | B5: 1 | C5: 1,50 m: dos niveles de 750 mm sobre B3 único.
A6: Basurero cierre lento, 1 contenedor (HSO460-30) | B6: 1 | C6: Módulo 300; confirmar fijación del frente extraíble, pues B1 no tiene bisagras asignadas.
A7: Canasta bajo fregadero (HSO228-90R) | B7: 1 | C7: Módulo 900; confirmar montaje independiente detrás de dos puertas, bisagras y sifón.
A8: Cubiertero HSC910-40 · 360 × 480 × 50 mm | B8: 1 | C8: B3 interior 663 × 520; cubiertero 360 × 480 a izquierda, apoyado sobre base aplicada de 15. Altura interior superior 75; cubiertero alto 50. Sin divisor fijo.
A9: Platero HSO566-03G · nominal 700 mm, gris antracita | B9: 1 | C9: HSO566-03G, 680 × 245 en luz 685: holgura total 5 mm. 7 kg máx.; acero 201 pintado. Fijación por pines: 4 taladros Ø10 según ficha transcrita. Marcar en obra con herraje real; profundidad según sistema, sin perforar de fábrica.
A10: Pata niveladora para zócalo 100 mm | B10: 24 | C10: 4 módulos bajos: 16 apoyos básicos + 8 refuerzos previstos para cajonero ancho, horno y lavaplatos. Distribución final según cargas; 24 apoyos conservados en presupuesto.
A11: Colgador regulable para gabinete superior (par) | B11: 4 | C11: Un par por gabinete
A12: Soporte de entrepaño | B12: 12 | C12: S1: 1 entrepaño · S3: 2 entrepaños (con división central)
A13: Tornillo 4 × 50 mm para armado | B13: 150 | C13: Aprox.; o minifix si prefieres armado desmontable
A14: Tornillo 4 × 16 mm para herrajes | B14: 150 | C14: 150 tornillos 4 × 16 aproximados para otros herrajes. Los 3 pares HRE550-55N incluyen 36 tornillos 4 × 12 mm según ficha transcrita; no comprarlos aparte ni contarlos como fijaciones de bases.
A16: Riel seleccionado · referencia única
A17: Referencia / marca | B17: Carga (kg) | C17: Selección y fuente
A18: HRE550-55N · Bonuit | B18: 30 | C18: Única referencia: HRE550-55N negro, 550, cierre lento, 30 kg, >25.000 ciclos. 3 pares a $47.034 = $141.102. Descuento 27 confirmado según ficha Bonuit rev. 15/05/2025 transcrita por usuario; caja 693. Altura 45 centrada. Confirmar ancho máximo y carga útil; fuente completa en Revisión.

Sheet Compras
A1: Grupo | B1: Ítem | C1: Cant. | D1: Precio unitario (COP) | E1: Subtotal (COP) | F1: Fuente / nota
A2: Tableros y cantos | B2: Tablero melamina Cartagena RH 15 mm, 2,15 × 2,44 | C2: 4 | D2: 365872 | E2: =IF(AND(ISNUMBER(C2),ISNUMBER(D2)),C2*D2,"Por cotizar") -> 1463488 | F2: Se conserva previsión de 4 láminas. Encaje geométrico verificado con piezas corregidas, refilado 10 mm y disco 4 mm, sin girar E/F; proveedor debe optimizar secuencia de corte y veta.
A3: Tableros y cantos | B3: Fondo melamina blanco nevado RH 6 mm, 2,15 × 2,44 | C3: 1 | D3: 212534 | E3: =IF(AND(ISNUMBER(C3),ISNUMBER(D3)),C3*D3,"Por cotizar") -> 212534 | F3: Se conserva 1 lámina de fondo. Encaje geométrico verificado con las 7 piezas actuales; confirmar formato del suministro antes del corte.
A4: Tableros y cantos | B4: Canto rígido Cartagena 19 × 2 mm · rollo 100 m | C4: =ROUNDUP(Cantos!F4/Cantos!H4,0) -> 1 | D4: 531600 | E4: =IF(AND(ISNUMBER(C4),ISNUMBER(D4)),C4*D4,"Por cotizar") -> 531600 | F4: Precio de la nueva versión: $531.600/rollo. Metros y rollos vinculados a Cantos; validar SKU.
A5: Tableros y cantos | B5: Canto flexible Cartagena 19 × 0,45 mm · rollo 200 m | C5: =ROUNDUP(Cantos!F5/Cantos!H5,0) -> 1 | D5: 285600 | E5: =IF(AND(ISNUMBER(C5),ISNUMBER(D5)),C5*D5,"Por cotizar") -> 285600 | F5: Precio de la nueva versión: $285.600/rollo. Metros y rollos vinculados a Cantos; validar SKU.
A6: Herrajes | B6: Perfil gola superior × 3 m | C6: 1 | D6: 41215 | E6: =IF(AND(ISNUMBER(C6),ISNUMBER(D6)),C6*D6,"Por cotizar") -> 41215 | F6: Madecentro
A7: Herrajes | B7: Perfil gola media × 3 m | C7: 1 | D7: 51014 | E7: =IF(AND(ISNUMBER(C7),ISNUMBER(D7)),C7*D7,"Por cotizar") -> 51014 | F7: Madecentro
A8: Herrajes | B8: Riel Bonuit HRE550-55N · negro · 550 mm · cierre lento 30 kg · par | C8: 3 | D8: 47034 | E8: =IF(AND(ISNUMBER(C8),ISNUMBER(D8)),C8*D8,"Por cotizar") -> 141102 | F8: HRE550-55N negro 550, 3 pares a $47.034 = $141.102. Descuento total 27 mm confirmado según ficha transcrita por usuario (Bonuit rev. 15/05/2025): vano 720 → caja 693. Riel 45 alto y 12,7 ancho, juego 13,5/lado. 30 kg, >25.000 ciclos; 36 tornillos 4 × 12 incluidos. Validar ancho máximo de cajón y carga útil. Precio verificado previamente en selector Madecentro.
A9: Herrajes | B9: Bisagra parche HBM897-01 · par (16 bisagras físicas) | C9: =Herrajes!B2/2 -> 8 | D9: 17750 | E9: =IF(AND(ISNUMBER(C9),ISNUMBER(D9)),C9*D9,"Por cotizar") -> 142000 | F9: Madecentro, consulta 25/10/2026: $17.750/par. Incluye tornillos; confirmar cotización.
A10: Herrajes | B10: Basurero cierre lento, 1 contenedor (HSO460-30) | C10: 1 | D10: 206135 | E10: =IF(AND(ISNUMBER(C10),ISNUMBER(D10)),C10*D10,"Por cotizar") -> 206135 | F10: Madecentro
A11: Herrajes | B11: Canasta bajo fregadero (HSO228-90R) | C11: 1 | D11: 193570 | E11: =IF(AND(ISNUMBER(C11),ISNUMBER(D11)),C11*D11,"Por cotizar") -> 193570 | F11: Madecentro
A12: Herrajes | B12: Platero HSO566-03G · nominal 700 mm · herraje 680 × 245 | C12: 1 | D12: 63539 | E12: =IF(AND(ISNUMBER(C12),ISNUMBER(D12)),C12*D12,"Por cotizar") -> 63539 | F12: HSO566-03G gris antracita: precio conservado $63.539. Ficha transcrita por usuario: 680 × 245, carga máxima 7 kg, acero 201 pintado, cuatro fijaciones Ø10; cotas y profundidad de taladro a verificar con pieza real. Marcar en obra.
A13: Herrajes | B13: Cubiertero HSC910-40 · 360 × 480 × 50 mm | C13: 1 | D13: 38791 | E13: =IF(AND(ISNUMBER(C13),ISNUMBER(D13)),C13*D13,"Por cotizar") -> 38791 | F13: Se conserva HSC910-40 de 360 × 480 × 50 y precio $38.791. Se coloca a un lado de B3, con apoyo antideslizante removible; no requiere panel divisor.
A14: Herrajes | B14: Pata niveladora para zócalo 100 mm | C14: 24 | D14: 2042 | E14: =IF(AND(ISNUMBER(C14),ISNUMBER(D14)),C14*D14,"Por cotizar") -> 49008 | F14: Madecentro
A15: Herrajes | B15: Colgador regulable para gabinete superior (par) | C15: 4 | D15: cotizar | E15: =IF(AND(ISNUMBER(C15),ISNUMBER(D15)),C15*D15,"Por cotizar") -> Por cotizar | F15: cotizar
A16: Herrajes | B16: Soportes de entrepaño y tornillería | C16: 1 | D16: cotizar | E16: =IF(AND(ISNUMBER(C16),ISNUMBER(D16)),C16*D16,"Por cotizar") -> Por cotizar | F16: 12 soportes, tornillos de armado y herrajes, fijaciones de fondos de 6, anclajes al muro y remates gola/zócalo. Evitar duplicar los incluidos.
A17: Mesón y equipos | B17: Mesón Crema Marfil 260 × 62 cm · código 519014 | C17: 1 | D17: 1486300 | E17: =IF(AND(ISNUMBER(C17),ISNUMBER(D17)),C17*D17,"Por cotizar") -> 1486300 | F17: Placa de 15 mm confirmada por usuario y ficha Homecenter. Precio $1.486.300 conservado. Recortes, material final, apoyos y posible borde engrosado por definir. La ficha mezcla 260/150 cm y granito/cuarzo: confirmar suministro concreto. https://www.homecenter.com.co/homecenter-co/product/519014/meson-granito-natural-crema-marfil-260-cm-x-62-cm/519014/
A18: Mesón y equipos | B18: Lavaplatos Socoda AS350 satinado · submontar 1 poceta 55 × 43 cm · código 87730 | C18: 1 | D18: 209900 | E18: =IF(AND(ISNUMBER(C18),ISNUMBER(D18)),C18*D18,"Por cotizar") -> 209900 | F18: Socoda AS350 satinado, código 87730: $209.900 conservados. 550 × 430 EXTERIORES, profundidad 165 mm. Abertura interior 490 × 370 según ficha descrita por usuario. Submontar: pestaña bajo placa, con anclaje/soporte compatibles. Hueco de corte lo define plantilla Socoda y acabado del borde; 490 × 370 solo referencia 3D. https://www.homecenter.com.co/homecenter-co/product/87730/lavaplatos-de-submontar-1-poceta-55x43-cm-acero-inoxidable-socoda/87730/
A19: Mesón y equipos | B19: Combo CA3057: campana Tofu negro 60 cm + horno H60EEVAL005 + estufa CCR60-F4P-SBF031 | C19: 1 | D19: 1864800 | E19: =IF(AND(ISNUMBER(C19),ISNUMBER(D19)),C19*D19,"Por cotizar") -> 1864800 | F19: Precio aportado por el usuario el 25/10/2026 por el combo completo. Horno mixto 110 V/gas natural; estufa cristal gas natural 60 × 51 cm.
A20: Servicios | B20: Corte y canteado de piezas | C20: 1 | D20: cotizar | E20: =IF(AND(ISNUMBER(C20),ISNUMBER(D20)),C20*D20,"Por cotizar") -> Por cotizar | F20: Cotizar corte, canteado y uniones de bases inferiores. EXCLUIR los 4 taladros Ø10 del platero del pedido a fábrica: marcar y ejecutar en obra con herraje real, verificando profundidad y posición. No duplicar rollos de canto ni tornillos de riel incluidos.
A21: Servicios | B21: Cortes y pulido del mesón (lavaplatos y estufa) | C21: 1 | D21: cotizar | E21: =IF(AND(ISNUMBER(C21),ISNUMBER(D21)),C21*D21,"Por cotizar") -> Por cotizar | F21: Plantillas y recortes en placa 15 mm. Lavaplatos 550 × 430 exterior NO es medida de hueco; referencia 3D 490 × 370, plantilla Socoda y tipo de borde mandan. Profundidad 165. Marmolero define radios, tolerancias, apoyos y anclajes; recorte estufa sigue por manual. Borde engrosado opcional por cotizar.
A22: Mesón y equipos | B22: Grifería de cocina | C22: 1 | D22: cotizar | E22: =IF(AND(ISNUMBER(C22),ISNUMBER(D22)),C22*D22,"Por cotizar") -> Por cotizar | F22: Seleccionar modelo y conexiones.
A23: Mesón y equipos | B23: Desagüe, canastilla, sifón y acoples | C23: 1 | D23: cotizar | E23: =IF(AND(ISNUMBER(C23),ISNUMBER(D23)),C23*D23,"Por cotizar") -> Por cotizar | F23: Revisar contra cubeta y canasta extraíble; evitar duplicados del suministro.
A24: Mesón y equipos | B24: Ducto y accesorios de campana | C24: 1 | D24: cotizar | E24: =IF(AND(ISNUMBER(C24),ISNUMBER(D24)),C24*D24,"Por cotizar") -> Por cotizar | F24: Definir según modelo Haceb, diámetro y salida.
A25: Servicios | B25: Armado e instalación de muebles y mesón | C25: 1 | D25: cotizar | E25: =IF(AND(ISNUMBER(C25),ISNUMBER(D25)),C25*D25,"Por cotizar") -> Por cotizar | F25: Cotizar nivelación, apoyos definidos por fabricante, fijación/sellado con producto compatible, soporte mecánico del lavaplatos y montaje de equipos. Transporte/manipulación según proveedor; no presupone dos operarios suficientes.
A26: Servicios | B26: Transporte y subida de materiales | C26: 1 | D26: cotizar | E26: =IF(AND(ISNUMBER(C26),ISNUMBER(D26)),C26*D26,"Por cotizar") -> Por cotizar | F26: Ingresar 0 únicamente si se confirma incluido.
B28: Subtotal tableros y cantos | E28: =SUMIF(A2:A26,"Tableros y cantos",E2:E26) -> 2493222
B29: Subtotal herrajes con precio | E29: =SUMIF(A2:A26,"Herrajes",E2:E26) -> 926374
B30: Subtotal mesón y equipos con precio | E30: =SUMIF(A2:A26,"Mesón y equipos",E2:E26) -> 3561000
B31: Subtotal servicios con precio | E31: =SUMIF(A2:A26,"Servicios",E2:E26) -> 0
B32: TOTAL CONOCIDO | E32: =SUM(E2:E26) -> 6980596 | F32: Subtotal parcial: no representa costo final. Cero en servicios significa sin importes cotizados.
B33: Partidas sin precio | E33: =ROWS(D2:D26)-COUNT(D2:D26) -> 9
B34: TOTAL DEL ALCANCE LISTADO | E34: =IF(E33=0,E32,"Pendiente de cotizaciones") -> Pendiente de cotizaciones | F34: Aun con todos los precios, validar alcances, IVA y posibles adecuaciones de agua/gas/electricidad.
B36: Precio unitario numérico = editable. Escribir 0 solo cuando se confirme gratuito o incluido.
B37: Si agregas partidas después de la fila 26, amplía las fórmulas de resumen.

Sheet Cantos
A1: Resumen de canto Cartagena 19 mm (tablero de 15 mm)
H2: Reserva por borde (m) | I2: 0.05
A3: Tipo | B3: Dónde va | C3: Metros netos | D3: Bordes | E3: Reserva de máquina (supuesto) | F3: Metros a pedir | H3: m por rollo
A4: Rígido (≈2 mm) | B4: Frentes y puertas en sus 4 lados; borde frontal de laterales, pisos, techos, entrepaños y costado; borde inferior de laterales de superiores | C4: =SUMPRODUCT(Despiece!$G$5:$G$79,Despiece!$E$5:$E$79,(Despiece!$H$5:$H$79="2")+(Despiece!$I$5:$I$79="2"))/1000+SUMPRODUCT(Despiece!$G$5:$G$79,Despiece!$F$5:$F$79,(Despiece!$J$5:$J$79="2")+(Despiece!$K$5:$K$79="2"))/1000 -> 50.263 | D4: =SUMPRODUCT(Despiece!$G$5:$G$79,(Despiece!$H$5:$H$79="2")+(Despiece!$I$5:$I$79="2")+(Despiece!$J$5:$J$79="2")+(Despiece!$K$5:$K$79="2")) -> 93 | E4: =D4*$I$2 -> 4.65 | F4: =ROUNDUP((C4+E4)/5,0)*5 -> 55 | H4: 100
A5: Flexible (≈0,45 mm) | B5: Bordes ocultos: traseros, superiores bajo el mesón, travesaños, cajas de cajón y zócalo | C5: =SUMPRODUCT(Despiece!$G$5:$G$79,Despiece!$E$5:$E$79,(Despiece!$H$5:$H$79="0.45")+(Despiece!$I$5:$I$79="0.45"))/1000+SUMPRODUCT(Despiece!$G$5:$G$79,Despiece!$F$5:$F$79,(Despiece!$J$5:$J$79="0.45")+(Despiece!$K$5:$K$79="0.45"))/1000 -> 95.267 | D5: =SUMPRODUCT(Despiece!$G$5:$G$79,(Despiece!$H$5:$H$79="0.45")+(Despiece!$I$5:$I$79="0.45")+(Despiece!$J$5:$J$79="0.45")+(Despiece!$K$5:$K$79="0.45")) -> 207 | E5: =D5*$I$2 -> 10.35 | F5: =ROUNDUP((C5+E5)/5,0)*5 -> 110 | H5: 200
A7: Piezas estrechas: validar proceso de canteado
A8: N° | B8: Pieza | C8: Medida (mm) | D8: Qué hacer
A9: 74 | B9: S4 Platero 71,5 · Listón inferior delantero | C9: 685 × 60 | D9: Conservar canto y protección de bordes: zona próxima al goteo del platero. Validar proceso para 60 mm.
A13: Los 5 cm por borde son una reserva editable; confirmar con la canteadora. No retirar cantos por estar ocultos.
A14: Neto calculado con dimensiones terminadas. El proveedor debe validar formato, espesor 19 × 2 / 19 × 0,45 y precios.

Sheet Revisión
A2: Correcciones y pendientes de fabricación
A4: Estado | B4: Tema | C4: Cambio o acción | D4: Ubicación | E4: Base / fuente
A5: Aplicado | B5: Riel y cajas | C5: B3: vano 720 − descuento confirmado 27 = caja exterior 693; interior 663 × 520. Descuento confirmado para HRE550-55N según ficha transcrita. Se conservan tres bases inferiores 693 × 550 y paredes 205/125/75. | D5: Despiece B3; Herrajes 3 | E5: Datos de ficha HRE550-55N Bonuit, rev. 15/05/2025, transcritos por el usuario el 25/10/2026. Documento original no adjunto en este turno.
A6: Aplicado | B6: Descuento de canto | C6: E/F se interpretan como dimensiones terminadas. L/M calculan corte teórico descontando cantos de extremos perpendiculares. Validar convención y tolerancias con proveedor. | D6: Despiece A2:A3, L:M | E6: Convención adoptada para conservar encajes nominales; requiere validación del proveedor.
A7: Aplicado | B7: Cantos | C7: Se conserva nuevo rollo rígido de 100 m a $531.600 y flexible de 200 m a $285.600. Resumen y compra enlazados a piezas. | D7: Cantos C4:F5; Compras C4:C5 | E7: Precios y presentaciones de la nueva versión suministrada.
A8: Aplicado | B8: Bisagras | C8: 16 unidades físicas = 8 pares. HBM897-01 a $17.750/par, referencia de consulta; validar peso de puertas y vigencia. | D8: Herrajes 2; Compras 9 | E8: https://madecentro.com/products/bisagra-parche-cierre-lento-clip-on-acero-inoxidable-201-35mm
A9: Aplicado | B9: Fórmulas | C9: Cada partida tiene fórmula; precio pendiente no equivale a cero. Se agregan gastos faltantes y total incompleto visible. | D9: Compras E2:E34 | E9: Recálculo independiente.
A10: Aplicado | B10: Conteos | C10: 75 piezas de melamina + 7 fondos = 82. Se retiran las 16 partidas IDs 30–45 del B4; se conservan los demás IDs. | D10: Despiece B3; Herrajes; Distribución | E10: Cantidades del despiece.
A11: Pendiente | B11: Platero | C11: Ficha transcrita HSO566-03G: 680 × 245 para módulo nominal 700 × 300, 7 kg máx., acero 201 pintado. S4 propuesto 715/luz 685: 5 mm de juego total; confirmar fijación con pieza real. 4 taladros Ø10 por pines, marcados en obra; profundidad y cotas no especificadas, excluirlos del mecanizado de fábrica. | D11: Herrajes 9; Compras 12 | E11: Ficha HSO566-03G descrita por usuario el 25/10/2026; original no adjunto en este turno.
A12: Aplicado | B12: Espesor mesón | C12: Placa de 15 mm confirmada por usuario y ficha de 519014. Se mantiene apoyo en y=885 y cara superior en y=900. Esta confirmación no aprueba recortes, apoyos ni material del suministro. | D12: Compras 17 | E12: https://www.homecenter.com.co/homecenter-co/product/519014/meson-granito-natural-crema-marfil-260-cm-x-62-cm/519014/
A13: Pendiente | B13: Patas y terminal | C13: Terminal 882 × 595 a 3 mm del piso. Se mantienen 24 patas: cuatro módulos básicos y ocho refuerzos; disponer apoyos bajo extremos del cajonero ancho y cargas de horno/lavaplatos. | D13: Despiece B3; Herrajes; Distribución | E13: No cambiar altura sin nivel de obra.
A14: Pendiente | B14: Gola y alturas | C14: Frentes 676 + holguras 9 + ranuras visibles 100 = caja 785. Mantener sección y mecanizados gola. Superiores: frente 717 sobre cuerpo 700; validar agarre y bisagras. | D14: Despiece; Herrajes 4:5 | E14: Dibujar sección gola y ubicación de frentes.
A15: Aplicado | B15: Alineación superior | C15: S1 pasa de 320 a 315: x=215–530, alineado con B6. S2/B2 mantienen x=530–1130; S3 845 y S4 715 sin cambios. | D15: Despiece S1; Distribución | E15: Corrección geométrica: S2/B2 coinciden independientemente del ancho de S1.
... A24: Aplicado | B24: Optimización | C24: Encaje sin solapes de 75 piezas de 15 mm en 4 láminas y 7 fondos en 1. Formato 2440 × 2150, refilado 10 mm y reserva de sierra 4 mm, orientación E/F fija. No se certifica mínimo de láminas ni secuencia de seccionadora. | D24: Despiece; Compras 2:3 | E24: Formato 2440 × 2150; refilado 10 mm por lado; sierra 4 mm; orientación E/F fija, sin rotación. Encaje geométrico sin solapes; no garantiza secuencia de seccionadora ni continuidad de veta.
A25: Aclaración | B25: Basurero | C25: El frente del basurero no lleva bisagras: se atornilla a los soportes de frente del herraje HSO460. | D25: Herrajes 6
A26: Aplicado | B26: Mesón: código | C26: Se selecciona 519014 de 260 × 62 cm por $1.486.300; reemplaza códigos y precios del mesón anterior de 280. | D26: Compras 17 | E26: Selección y precio del usuario: código 519014.
A27: Aplicado | B27: Lavaplatos: precio | C27: Socoda AS350, código 87730: se conserva $209.900 porque el usuario lo aportó expresamente para este modelo. | D27: Compras 18
A28: Aplicado | B28: Cubiertero: código | C28: HSC910-40: 360 × 480 × 50. En interior 663 × 520, a un lado del cajón superior. Confirmar medida real y altura; fijación removible antideslizante, sin divisor fijo. | D28: Despiece B3; Herrajes; Distribución
A29: Aplicado | B29: Holgura esquina | C29: Mesón 2600 centrado en muro 3000: 200 mm libres a cada extremo. Bajos a 220 y superiores a 310 de esquina derecha. Vuelos conservados 15 izquierda y 20 derecha. | D29: Distribución | E29: Mesón de 260 cm seleccionado por el usuario; vuelos conservados.
A30: Aplicado | B30: Rellenos eliminados | C30: Sin B0 ni S0. Dos zócalos de 1275 cubren 2550 bajo B1/B2/B3/B5; el cajonero único ocupa x=1130–1880. | D30: Despiece B3; Herrajes; Distribución | E30: Se conserva el ancho útil de cada módulo.
A31: Aplicado | B31: HTML coherente | C31: Hueco ilustrativo 490 × 370 y pestaña exterior 550 × 430 bajo placa; cubeta 165 de profundidad, fondo interior a 720. B5 con travesaños 870 × 100 de canto, fuera de pestaña. Se mantienen bases inferiores de cajón, S1 alineado y resto de geometría. | D31: Cocina Cartagena 3D.html | E31: Dimensiones terminadas de este XLSX.
A32: Aplicado | B32: Bases inferiores B3 | C32: Base B3 aplicada inferior 693 × 550 × 15, bajo las cuatro paredes. Paredes antes 220/140/90 pasan a 205/125/75. Envolventes totales conservadas 220/140/90; alturas interiores iguales. Unión por cara inferior con pretaladro a paredes: proveedor define fijaciones, separaciones y refuerzos según carga; no es cálculo estructural. | D32: Despiece IDs 21–29 | E32: Solución de ensamblaje propuesta; validación de uniones y carga por fabricante pendiente.
A33: Pendiente | B33: Mesón: recortes y apoyos | C33: 3D corrige hueco del lavaplatos a referencia 490 × 370, centro x=2330/z=310, franjas frontal y posterior 125. Exterior 550 × 430 con pestaña inferior: no usar como hueco. Corte final según plantilla Socoda y marmolero (radios/reveal/tolerancias). Travesaños B5 se representan de canto; validar listones y soporte mecánico definitivo. Estufa pendiente de plantilla/manual. | D33: B2/B5; Compras 21,25 | E33: Sin aprobación de recortes ni cálculo de cargas; no adoptar 10 mm como radio mínimo universal.
A34: Pendiente | B34: Submontaje 15 mm | C34: Verificar compatibilidad de anclajes Socoda con placa de 15 mm y soporte mecánico para peso del lavaplatos, agua y uso. Definir sellado/fijación y adhesivo compatible con fabricante; no depender de una recomendación genérica de silicona. | D34: Compras 18,23,25 | E34: Plantilla, kit y manual de instalación del lavaplatos por confirmar.
A35: Opcional | B35: Borde engrosado | C35: Placa 15 mm puede tener faldón o borde armado de apariencia 30 mm, si lo admite el proveedor. No equivale a placa maciza de 30. Mantener cara superior 900; si baja a 870, revisar interferencias con gola, panel del horno y apertura de frentes. Modelo conserva borde simple hasta elegir perfil y sección. | D35: Mesón; B2; gola; Compras 21 | E35: Opción del usuario sin dimensiones de sección ni precio confirmados.

Sheet Distribución
A2: Distribución con mesón de 260 cm · holguras de 20 cm
A3: Muro (mm) | B3: 3000
A4: Mesón (mm) | B4: 2600
A5: Separación mesón-esquina (mm) | B5: 200
A6: Inicio mesón desde extremo izquierdo | B6: =B3-B5-B4 -> 200
A7: Final mesón desde extremo izquierdo | B7: =B3-B5 -> 2800
A8: Vuelo mesón sobre costado libre (mm) | B8: 15
A11: Elemento | B11: Inicio x (mm) | C11: Final x (mm) | D11: Ancho (mm) | E11: Alto (mm) | F11: Fondo (mm) | G11: Colocación | H11: Origen
A12: Mesón | B12: =B6 -> 200 | C12: =B7 -> 2800 | D12: =B4 -> 2600 | E12: 15 | F12: 620 | G12: Placa de 15 mm confirmada: cara inferior 885, superior 900. Recortes, apoyos y perfil del borde por definir con marmolero. | H12: Compras, medida nominal
A13: B6 · Costado libre | B13: =B6+B8 -> 215 | C13: =B13+D13 -> 230 | D13: 15 | E13: =Despiece!E38 -> 882 | F13: =Despiece!F38 -> 595 | G13: Desde y=3 hasta 885: deja 3 mm sobre el piso. | H13: Despiece
A14: B1 · Basurero | B14: =C13 -> 230 | C14: =B14+D14 -> 530 | D14: =Despiece!E6+30 -> 300 | E14: 785 | F14: 580 | G14: Patas a 100 mm; frente a 100–832. | H14: Despiece
A15: B2 · Horno | B15: =C14 -> 530 | C15: =B15+D15 -> 1130 | D15: =Despiece!E11+30 -> 600 | E15: 785 | F15: 580 | G15: Nicho y ventilación sujetos al manual. | H15: Despiece
A16: B3 · Cajonero único 75 | B16: =C15 -> 1130 | C16: =B16+D16 -> 1880 | D16: =Despiece!E17+30 -> 750 | E16: 785 | F16: 580 | G16: B3 750; cajas exteriores 693 × 550. Base aplicada 15 debajo de paredes: alturas 205/125/75, envolventes 220/140/90. Interior 663 × 520; cubiertero lateral 360 × 480. | H16: Despiece
A18: B5 · Lavaplatos | B18: =C16 -> 1880 | C18: =B18+D18 -> 2780 | D18: =Despiece!E33+30 -> 900 | E18: 785 | F18: 580 | G18: B5 900. Travesaños de 870 × 100 de canto: 15 de fondo y 100 de alto. Pestaña exterior del lavaplatos 550 × 430 debajo de placa; abertura 3D 490 × 370. Dos listones 870 × 80 del despiece conservados; posición/anclaje de apoyo por validar. | H18: Despiece
A19: S1 · Alacena 31,5 | B19: =B20-D19 -> 215 | C19: =B20 -> 530 | D19: =Despiece!E41+30 -> 315 | E19: 700 | F19: 320 | G19: S1 315: x=215–530, alineado con costado B6. Cuerpo 1450–2150; frente 1430–2147. S2/B2 conservan x=530–1130. | H19: Despiece
A20: S2 · Ducto | B20: =B15 -> 530 | C20: =B20+D20 -> 1130 | D20: =Despiece!E47+30 -> 600 | E20: 350 | F20: 320 | G20: Cuerpo 1800–2150; campana ilustrativa a 1550. | H20: Despiece
A21: S3 · Alacena | B21: =C20 -> 1130 | C21: =B21+D21 -> 1975 | D21: =Despiece!E52+30 -> 845 | E21: 700 | F21: 320 | G21: 845 mm; división central, dos entrepaños de 397,5. | H21: Despiece
A22: S4 · Platero | B22: =C21 -> 1975 | C22: =B22+D22 -> 2690 | D22: =Despiece!E59+30 -> 715 | E22: 700 | F22: 320 | G22: S4 715, luz 685; herraje 680 × 245, 5 mm de holgura total, máximo 7 kg. Pines: 4 agujeros Ø10 marcados en obra; sin taladros de fábrica. | H22: Despiece
A25: Libre a la izquierda del mesón (mm) | B25: =B12 -> 200
A26: Libre mesón-esquina (mm) | B26: =B3-C12 -> 200
A27: Libre bajos-esquina (mm) | B27: =B3-C18 -> 220
A28: Libre superiores-esquina (mm) | B28: =B3-C22 -> 310
A30: Mesón centrado: 200 mm libres a cada extremo del muro. Bajos terminan en x=2780; superiores en x=2690.
A31: Coordenada x desde el extremo izquierdo del muro de 3000 mm. Esquina en x=3000. No se cambian alturas de equipos sin sus manuales.
A32: Se retiran los IDs 30–45 del B4; B3 se amplía a 750. Se mantienen los otros IDs para trazabilidad.
A33: Bases B3 bajo las paredes, sin aumentar la envolvente vertical. Antes de cortar: validar unión, carga, rieles, espesor de mesón y anclajes del platero.
