Workbook

Sheet Despiece
A2: Clóset principal 195: despiece independiente
A3: Cuerpo 195 × 56 × 238 cm; 58,5 cm hasta las manijas. RH15 como cocina. Despiece exclusivo del clóset.
A4: E/F: medidas terminadas y veta en E. I/J paralelos a E, K/L paralelos a F. Cortes teóricos sin sierra ni refilado.
A6: ID | B6: Grupo | C6: Pieza | D6: Cant. | E6: Largo veta mm | F6: Ancho mm | G6: Espesor mm | H6: Área m² | I6: Canto L1 | J6: Canto L2 | K6: Canto A1 | L6: Canto A2 | M6: Corte largo mm | N6: Corte ancho mm | O6: Estado | P6: Nota de fabricación
A7: C3-001 | B7: EST | C7: Lateral exterior | D7: 2 | E7: 2280 | F7: 560 | G7: 15 | H7: =D7*E7*F7/1000000 -> 2.5536 | I7: 2 | J7: — | K7: 0.45 | L7: 0.45 | M7: =E7-IF(K7="2",2,IF(K7="0.45",0.45,0))-IF(L7="2",2,IF(L7="0.45",0.45,0)) -> 2279.1 | N7: =F7-IF(I7="2",2,IF(I7="0.45",0.45,0))-IF(J7="2",2,IF(J7="0.45",0.45,0)) -> 558 | O7: Diseño elegido | P7: Cuerpo de 56 cm; hojas hasta 55 cm. Las manijas sobresalen hasta 58,5 cm desde el fondo.
A8: C3-002 | B8: EST | C8: Divisor central | D8: 1 | E8: 2280 | F8: 490 | G8: 15 | H8: =D8*E8*F8/1000000 -> 1.1172 | I8: 2 | J8: — | K8: 0.45 | L8: — | M8: =E8-IF(K8="2",2,IF(K8="0.45",0.45,0))-IF(L8="2",2,IF(L8="0.45",0.45,0)) -> 2279.55 | N8: =F8-IF(I8="2",2,IF(I8="0.45",0.45,0))-IF(J8="2",2,IF(J8="0.45",0.45,0)) -> 488 | O8: Diseño elegido | P8: Divisor de 49 cm: deja 10 mm respecto a la hoja interior, ubicada a 50 cm del fondo.
A9: C3-003 | B9: B1 | C9: Piso sobre base | D9: 1 | E9: 830 | F9: 560 | G9: 15 | H9: =D9*E9*F9/1000000 -> 0.4648 | I9: 2 | J9: — | K9: 0.45 | L9: — | M9: =E9-IF(K9="2",2,IF(K9="0.45",0.45,0))-IF(L9="2",2,IF(L9="0.45",0.45,0)) -> 829.55 | N9: =F9-IF(I9="2",2,IF(I9="0.45",0.45,0))-IF(J9="2",2,IF(J9="0.45",0.45,0)) -> 558 | O9: Diseño elegido | P9: Uniones y mecanizados según montaje.
A10: C3-004 | B10: B1 | C10: Tapa superior | D10: 1 | E10: 830 | F10: 505 | G10: 15 | H10: =D10*E10*F10/1000000 -> 0.41915 | I10: 0.45 | J10: — | K10: — | L10: — | M10: =E10-IF(K10="2",2,IF(K10="0.45",0.45,0))-IF(L10="2",2,IF(L10="0.45",0.45,0)) -> 830 | N10: =F10-IF(I10="2",2,IF(I10="0.45",0.45,0))-IF(J10="2",2,IF(J10="0.45",0.45,0)) -> 504.55 | O10: Diseño elegido | P10: Tapa de 505 mm: llega hasta el listón de pino 4×4 cm (P3-01), que sostiene el riel. Se une a laterales y divisor; el listón queda a ras de su cara superior.
A11: C3-005 | B11: B1 | C11: Fondo RH15 | D11: 1 | E11: 2250 | F11: 830 | G11: 15 | H11: =D11*E11*F11/1000000 -> 1.8675 | I11: — | J11: — | K11: — | L11: — | M11: =E11-IF(K11="2",2,IF(K11="0.45",0.45,0))-IF(L11="2",2,IF(L11="0.45",0.45,0)) -> 2250 | N11: =F11-IF(I11="2",2,IF(I11="0.45",0.45,0))-IF(J11="2",2,IF(J11="0.45",0.45,0)) -> 830 | O11: Diseño elegido | P11: Panel trasero del mismo RH15 y acabado. Útil de colgado hasta la hoja trasera: 485 mm.
A12: C3-006 | B12: B1 | C12: Piso de maletero | D12: 1 | E12: 830 | F12: 475 | G12: 15 | H12: =D12*E12*F12/1000000 -> 0.39425 | I12: 2 | J12: — | K12: — | L12: — | M12: =E12-IF(K12="2",2,IF(K12="0.45",0.45,0))-IF(L12="2",2,IF(L12="0.45",0.45,0)) -> 830 | N12: =F12-IF(I12="2",2,IF(I12="0.45",0.45,0))-IF(J12="2",2,IF(J12="0.45",0.45,0)) -> 473 | O12: Diseño elegido | P12: Maletero interior accesible por las hojas corredizas; carga liviana.
A13: C3-007 | B13: B1 | C13: Refuerzo frontal de maletero | D13: 1 | E13: 830 | F13: 80 | G13: 15 | H13: =D13*E13*F13/1000000 -> 0.0664 | I13: 0.45 | J13: — | K13: — | L13: — | M13: =E13-IF(K13="2",2,IF(K13="0.45",0.45,0))-IF(L13="2",2,IF(L13="0.45",0.45,0)) -> 830 | N13: =F13-IF(I13="2",2,IF(I13="0.45",0.45,0))-IF(J13="2",2,IF(J13="0.45",0.45,0)) -> 79.55 | O13: Diseño elegido | P13: De canto. Apoyos y unión al tablero por definir antes de fabricar.
A14: C3-008 | B14: B1 | C14: Refuerzo trasero de maletero | D14: 1 | E14: 830 | F14: 100 | G14: 15 | H14: =D14*E14*F14/1000000 -> 0.083 | I14: 0.45 | J14: — | K14: — | L14: — | M14: =E14-IF(K14="2",2,IF(K14="0.45",0.45,0))-IF(L14="2",2,IF(L14="0.45",0.45,0)) -> 830 | N14: =F14-IF(I14="2",2,IF(I14="0.45",0.45,0))-IF(J14="2",2,IF(J14="0.45",0.45,0)) -> 99.55 | O14: Diseño elegido | P14: De canto. No atribuir rigidez al pegado sobre canto decorativo.
A15: C3-009 | B15: B2 | C15: Piso sobre base | D15: 1 | E15: 1075 | F15: 560 | G15: 15 | H15: =D15*E15*F15/1000000 -> 0.602 | I15: 2 | J15: — | K15: 0.45 | L15: — | M15: =E15-IF(K15="2",2,IF(K15="0.45",0.45,0))-IF(L15="2",2,IF(L15="0.45",0.45,0)) -> 1074.55 | N15: =F15-IF(I15="2",2,IF(I15="0.45",0.45,0))-IF(J15="2",2,IF(J15="0.45",0.45,0)) -> 558 | O15: Diseño elegido | P15: Uniones y mecanizados según montaje.
A16: C3-010 | B16: B2 | C16: Tapa superior | D16: 1 | E16: 1075 | F16: 505 | G16: 15 | H16: =D16*E16*F16/1000000 -> 0.542875 | I16: 0.45 | J16: — | K16: — | L16: — | M16: =E16-IF(K16="2",2,IF(K16="0.45",0.45,0))-IF(L16="2",2,IF(L16="0.45",0.45,0)) -> 1075 | N16: =F16-IF(I16="2",2,IF(I16="0.45",0.45,0))-IF(J16="2",2,IF(J16="0.45",0.45,0)) -> 504.55 | O16: Diseño elegido | P16: Tapa de 505 mm: llega hasta el listón de pino 4×4 cm (P3-01), que sostiene el riel. Se une a laterales y divisor; el listón queda a ras de su cara superior.
A17: C3-011 | B17: B2 | C17: Fondo RH15 | D17: 1 | E17: 2250 | F17: 1075 | G17: 15 | H17: =D17*E17*F17/1000000 -> 2.41875 | I17: — | J17: — | K17: — | L17: — | M17: =E17-IF(K17="2",2,IF(K17="0.45",0.45,0))-IF(L17="2",2,IF(L17="0.45",0.45,0)) -> 2250 | N17: =F17-IF(I17="2",2,IF(I17="0.45",0.45,0))-IF(J17="2",2,IF(J17="0.45",0.45,0)) -> 1075 | O17: Diseño elegido | P17: Panel trasero del mismo RH15 y acabado. Útil de colgado hasta la hoja trasera: 485 mm.
A18: C3-012 | B18: B2 | C18: Piso de maletero | D18: 1 | E18: 1075 | F18: 475 | G18: 15 | H18: =D18*E18*F18/1000000 -> 0.510625 | I18: 2 | J18: — | K18: — | L18: — | M18: =E18-IF(K18="2",2,IF(K18="0.45",0.45,0))-IF(L18="2",2,IF(L18="0.45",0.45,0)) -> 1075 | N18: =F18-IF(I18="2",2,IF(I18="0.45",0.45,0))-IF(J18="2",2,IF(J18="0.45",0.45,0)) -> 473 | O18: Diseño elegido | P18: Maletero interior accesible por las hojas corredizas; carga liviana.
... A30: C3-024 | B30: EST | C30: Solapa frontal | D30: 1 | E30: 1950 | F30: 120 | G30: 15 | H30: =D30*E30*F30/1000000 -> 0.234 | I30: 2 | J30: 0.45 | K30: 2 | L30: 2 | M30: =E30-IF(K30="2",2,IF(K30="0.45",0.45,0))-IF(L30="2",2,IF(L30="0.45",0.45,0)) -> 1946 | N30: =F30-IF(I30="2",2,IF(I30="0.45",0.45,0))-IF(J30="2",2,IF(J30="0.45",0.45,0)) -> 117.55 | O30: Diseño elegido | P30: Cubre el frente superior (riel y borde alto de las hojas), como en el clóset real: 12 cm de alto, sobresale 15 mm delante del cuerpo de 56 cm. Se fija a los cantos delanteros de los laterales y a dos tacos de pino de 15 mm (sobrantes del listón) atornillados al frente del listón. Canto rígido abajo y en los extremos; el borde alto va contra el cielo raso.
C32: TOTAL RH15 | D32: =SUM(D7:D30) -> 44 | G32: Área neta | H32: =SUM(H7:H30) -> 18.99642
A33: Listón de pino (bastidor del riel) fuera de este total: ver hoja Compras.

Sheet Pedido de corte
S1: Observaciones fijas por pieza
A2: Pedido de corte y canteado · clóset principal 195 | P2: ¿El proveedor pide medida terminada y descuenta el canto? (SÍ/NO) | Q2: SÍ | S2: C3-001 | T2: Rebaje superior para el listón de pino 4 × 4 en taller.
A3: Medidas en mm; largo en sentido de veta. R = rígido 2 mm · F = flexible 0,45 mm · — = sin canto. Se cantean únicamente los bordes indicados; orientar las piezas según el montaje. | P3: Dimensión menor mínima de tablero que admite la canteadora (mm) | Q3: 100 | S3: C3-015 | T3: Veta horizontal: frente de 824 de ancho, queda detrás de las hojas.
A4: Piezas pequeñas: clasificación según el tamaño del tablero antes de cantear. Si la máquina las rechaza, usar el corte indicado en Observaciones y cantear en el armado. Medidas de corte a 0,01 mm; el proveedor confirma tolerancias y límites Q2–Q4. | P4: Dimensión mayor mínima de tablero que admite la canteadora (mm) | Q4: 250 | S4: C3-023 | T4: Cortar después de confirmar el kit Peralma (altura de hoja y plantilla).
P5: Supuestos por confirmar en la sucursal: Q2 cambia la medida que se pide; Q3 y Q4 marcan qué piezas pueden rechazar.
A6: ID | B6: Módulo / grupo | C6: Pieza | D6: Material | E6: Cant. | F6: Largo a pedir (veta) | G6: Ancho a pedir | H6: Largo 1 | I6: Largo 2 | J6: Corto 1 | K6: Corto 2 | L6: Canteo | M6: Medida terminada | N6: Observaciones
A7: =Despiece!A7 -> C3-001 | B7: =Despiece!B7 -> EST | C7: =Despiece!C7 -> Lateral exterior | D7: ="RH15 Cartagena "&Despiece!G7&" mm" -> RH15 Cartagena 15 mm | E7: =Despiece!D7 -> 2 | F7: =IF($Q$2="NO",ROUND(Despiece!M7,2),Despiece!E7) -> 2280 | G7: =IF($Q$2="NO",ROUND(Despiece!N7,2),Despiece!F7) -> 560 | H7: =IF(Despiece!I7="2","R",IF(Despiece!I7="0.45","F","—")) -> R | I7: =IF(Despiece!J7="2","R",IF(Despiece!J7="0.45","F","—")) -> — | J7: =IF(Despiece!K7="2","R",IF(Despiece!K7="0.45","F","—")) -> F | K7: =IF(Despiece!L7="2","R",IF(Despiece!L7="0.45","F","—")) -> F | L7: =IF(SUMPRODUCT((Despiece!I7:L7="2")+(Despiece!I7:L7="0.45"))=0,"Sin canto",IF(OR(MIN(Despiece!M7,Despiece!N7)<$Q$3,MAX(Despiece!M7,Despiece!N7)<$Q$4),"Pequeña","Normal")) -> Normal | M7: =Despiece!E7&" × "&Despiece!F7 -> 2280 × 560 | N7: =IF(LEN(TRIM(IF($L7="Pequeña","Si no la cantean: cortar a "&ROUND(Despiece!M7,2)&" × "&ROUND(Despiece!N7,2)&" y cantear en el armado.","")&" "&IFERROR(VLOOKUP(Despiece!A7,$S$2:$T$40,2,FALSE),"")))=0,"—",TRIM(IF($L7="Pequeña","Si no la cantean: cortar a "&ROUND(Despiece!M7,2)&" × "&ROUND(Despiece!N7,2)&" y cantear en el armado.","")&" "&IFERROR(VLOOKUP(Despiece!A7,$S$2:$T$40,2,FALSE),""))) -> Rebaje superior para el listón de pino 4 × 4 en taller.
A8: =Despiece!A8 -> C3-002 | B8: =Despiece!B8 -> EST | C8: =Despiece!C8 -> Divisor central | D8: ="RH15 Cartagena "&Despiece!G8&" mm" -> RH15 Cartagena 15 mm | E8: =Despiece!D8 -> 1 | F8: =IF($Q$2="NO",ROUND(Despiece!M8,2),Despiece!E8) -> 2280 | G8: =IF($Q$2="NO",ROUND(Despiece!N8,2),Despiece!F8) -> 490 | H8: =IF(Despiece!I8="2","R",IF(Despiece!I8="0.45","F","—")) -> R | I8: =IF(Despiece!J8="2","R",IF(Despiece!J8="0.45","F","—")) -> — | J8: =IF(Despiece!K8="2","R",IF(Despiece!K8="0.45","F","—")) -> F | K8: =IF(Despiece!L8="2","R",IF(Despiece!L8="0.45","F","—")) -> — | L8: =IF(SUMPRODUCT((Despiece!I8:L8="2")+(Despiece!I8:L8="0.45"))=0,"Sin canto",IF(OR(MIN(Despiece!M8,Despiece!N8)<$Q$3,MAX(Despiece!M8,Despiece!N8)<$Q$4),"Pequeña","Normal")) -> Normal | M8: =Despiece!E8&" × "&Despiece!F8 -> 2280 × 490 | N8: =IF(LEN(TRIM(IF($L8="Pequeña","Si no la cantean: cortar a "&ROUND(Despiece!M8,2)&" × "&ROUND(Despiece!N8,2)&" y cantear en el armado.","")&" "&IFERROR(VLOOKUP(Despiece!A8,$S$2:$T$40,2,FALSE),"")))=0,"—",TRIM(IF($L8="Pequeña","Si no la cantean: cortar a "&ROUND(Despiece!M8,2)&" × "&ROUND(Despiece!N8,2)&" y cantear en el armado.","")&" "&IFERROR(VLOOKUP(Despiece!A8,$S$2:$T$40,2,FALSE),""))) -> —
A9: =Despiece!A9 -> C3-003 | B9: =Despiece!B9 -> B1 | C9: =Despiece!C9 -> Piso sobre base | D9: ="RH15 Cartagena "&Despiece!G9&" mm" -> RH15 Cartagena 15 mm | E9: =Despiece!D9 -> 1 | F9: =IF($Q$2="NO",ROUND(Despiece!M9,2),Despiece!E9) -> 830 | G9: =IF($Q$2="NO",ROUND(Despiece!N9,2),Despiece!F9) -> 560 | H9: =IF(Despiece!I9="2","R",IF(Despiece!I9="0.45","F","—")) -> R | I9: =IF(Despiece!J9="2","R",IF(Despiece!J9="0.45","F","—")) -> — | J9: =IF(Despiece!K9="2","R",IF(Despiece!K9="0.45","F","—")) -> F | K9: =IF(Despiece!L9="2","R",IF(Despiece!L9="0.45","F","—")) -> — | L9: =IF(SUMPRODUCT((Despiece!I9:L9="2")+(Despiece!I9:L9="0.45"))=0,"Sin canto",IF(OR(MIN(Despiece!M9,Despiece!N9)<$Q$3,MAX(Despiece!M9,Despiece!N9)<$Q$4),"Pequeña","Normal")) -> Normal | M9: =Despiece!E9&" × "&Despiece!F9 -> 830 × 560 | N9: =IF(LEN(TRIM(IF($L9="Pequeña","Si no la cantean: cortar a "&ROUND(Despiece!M9,2)&" × "&ROUND(Despiece!N9,2)&" y cantear en el armado.","")&" "&IFERROR(VLOOKUP(Despiece!A9,$S$2:$T$40,2,FALSE),"")))=0,"—",TRIM(IF($L9="Pequeña","Si no la cantean: cortar a "&ROUND(Despiece!M9,2)&" × "&ROUND(Despiece!N9,2)&" y cantear en el armado.","")&" "&IFERROR(VLOOKUP(Despiece!A9,$S$2:$T$40,2,FALSE),""))) -> —
A10: =Despiece!A10 -> C3-004 | B10: =Despiece!B10 -> B1 | C10: =Despiece!C10 -> Tapa superior | D10: ="RH15 Cartagena "&Despiece!G10&" mm" -> RH15 Cartagena 15 mm | E10: =Despiece!D10 -> 1 | F10: =IF($Q$2="NO",ROUND(Despiece!M10,2),Despiece!E10) -> 830 | G10: =IF($Q$2="NO",ROUND(Despiece!N10,2),Despiece!F10) -> 505 | H10: =IF(Despiece!I10="2","R",IF(Despiece!I10="0.45","F","—")) -> F | I10: =IF(Despiece!J10="2","R",IF(Despiece!J10="0.45","F","—")) -> — | J10: =IF(Despiece!K10="2","R",IF(Despiece!K10="0.45","F","—")) -> — | K10: =IF(Despiece!L10="2","R",IF(Despiece!L10="0.45","F","—")) -> — | L10: =IF(SUMPRODUCT((Despiece!I10:L10="2")+(Despiece!I10:L10="0.45"))=0,"Sin canto",IF(OR(MIN(Despiece!M10,Despiece!N10)<$Q$3,MAX(Despiece!M10,Despiece!N10)<$Q$4),"Pequeña","Normal")) -> Normal | M10: =Despiece!E10&" × "&Despiece!F10 -> 830 × 505 | N10: =IF(LEN(TRIM(IF($L10="Pequeña","Si no la cantean: cortar a "&ROUND(Despiece!M10,2)&" × "&ROUND(Despiece!N10,2)&" y cantear en el armado.","")&" "&IFERROR(VLOOKUP(Despiece!A10,$S$2:$T$40,2,FALSE),"")))=0,"—",TRIM(IF($L10="Pequeña","Si no la cantean: cortar a "&ROUND(Despiece!M10,2)&" × "&ROUND(Despiece!N10,2)&" y cantear en el armado.","")&" "&IFERROR(VLOOKUP(Despiece!A10,$S$2:$T$40,2,FALSE),""))) -> —
A11: =Despiece!A11 -> C3-005 | B11: =Despiece!B11 -> B1 | C11: =Despiece!C11 -> Fondo RH15 | D11: ="RH15 Cartagena "&Despiece!G11&" mm" -> RH15 Cartagena 15 mm | E11: =Despiece!D11 -> 1 | F11: =IF($Q$2="NO",ROUND(Despiece!M11,2),Despiece!E11) -> 2250 | G11: =IF($Q$2="NO",ROUND(Despiece!N11,2),Despiece!F11) -> 830 | H11: =IF(Despiece!I11="2","R",IF(Despiece!I11="0.45","F","—")) -> — | I11: =IF(Despiece!J11="2","R",IF(Despiece!J11="0.45","F","—")) -> — | J11: =IF(Despiece!K11="2","R",IF(Despiece!K11="0.45","F","—")) -> — | K11: =IF(Despiece!L11="2","R",IF(Despiece!L11="0.45","F","—")) -> — | L11: =IF(SUMPRODUCT((Despiece!I11:L11="2")+(Despiece!I11:L11="0.45"))=0,"Sin canto",IF(OR(MIN(Despiece!M11,Despiece!N11)<$Q$3,MAX(Despiece!M11,Despiece!N11)<$Q$4),"Pequeña","Normal")) -> Sin canto | M11: =Despiece!E11&" × "&Despiece!F11 -> 2250 × 830 | N11: =IF(LEN(TRIM(IF($L11="Pequeña","Si no la cantean: cortar a "&ROUND(Despiece!M11,2)&" × "&ROUND(Despiece!N11,2)&" y cantear en el armado.","")&" "&IFERROR(VLOOKUP(Despiece!A11,$S$2:$T$40,2,FALSE),"")))=0,"—",TRIM(IF($L11="Pequeña","Si no la cantean: cortar a "&ROUND(Despiece!M11,2)&" × "&ROUND(Despiece!N11,2)&" y cantear en el armado.","")&" "&IFERROR(VLOOKUP(Despiece!A11,$S$2:$T$40,2,FALSE),""))) -> —
A12: =Despiece!A12 -> C3-006 | B12: =Despiece!B12 -> B1 | C12: =Despiece!C12 -> Piso de maletero | D12: ="RH15 Cartagena "&Despiece!G12&" mm" -> RH15 Cartagena 15 mm | E12: =Despiece!D12 -> 1 | F12: =IF($Q$2="NO",ROUND(Despiece!M12,2),Despiece!E12) -> 830 | G12: =IF($Q$2="NO",ROUND(Despiece!N12,2),Despiece!F12) -> 475 | H12: =IF(Despiece!I12="2","R",IF(Despiece!I12="0.45","F","—")) -> R | I12: =IF(Despiece!J12="2","R",IF(Despiece!J12="0.45","F","—")) -> — | J12: =IF(Despiece!K12="2","R",IF(Despiece!K12="0.45","F","—")) -> — | K12: =IF(Despiece!L12="2","R",IF(Despiece!L12="0.45","F","—")) -> — | L12: =IF(SUMPRODUCT((Despiece!I12:L12="2")+(Despiece!I12:L12="0.45"))=0,"Sin canto",IF(OR(MIN(Despiece!M12,Despiece!N12)<$Q$3,MAX(Despiece!M12,Despiece!N12)<$Q$4),"Pequeña","Normal")) -> Normal | M12: =Despiece!E12&" × "&Despiece!F12 -> 830 × 475 | N12: =IF(LEN(TRIM(IF($L12="Pequeña","Si no la cantean: cortar a "&ROUND(Despiece!M12,2)&" × "&ROUND(Despiece!N12,2)&" y cantear en el armado.","")&" "&IFERROR(VLOOKUP(Despiece!A12,$S$2:$T$40,2,FALSE),"")))=0,"—",TRIM(IF($L12="Pequeña","Si no la cantean: cortar a "&ROUND(Despiece!M12,2)&" × "&ROUND(Despiece!N12,2)&" y cantear en el armado.","")&" "&IFERROR(VLOOKUP(Despiece!A12,$S$2:$T$40,2,FALSE),""))) -> —
A13: =Despiece!A13 -> C3-007 | B13: =Despiece!B13 -> B1 | C13: =Despiece!C13 -> Refuerzo frontal de maletero | D13: ="RH15 Cartagena "&Despiece!G13&" mm" -> RH15 Cartagena 15 mm | E13: =Despiece!D13 -> 1 | F13: =IF($Q$2="NO",ROUND(Despiece!M13,2),Despiece!E13) -> 830 | G13: =IF($Q$2="NO",ROUND(Despiece!N13,2),Despiece!F13) -> 80 | H13: =IF(Despiece!I13="2","R",IF(Despiece!I13="0.45","F","—")) -> F | I13: =IF(Despiece!J13="2","R",IF(Despiece!J13="0.45","F","—")) -> — | J13: =IF(Despiece!K13="2","R",IF(Despiece!K13="0.45","F","—")) -> — | K13: =IF(Despiece!L13="2","R",IF(Despiece!L13="0.45","F","—")) -> — | L13: =IF(SUMPRODUCT((Despiece!I13:L13="2")+(Despiece!I13:L13="0.45"))=0,"Sin canto",IF(OR(MIN(Despiece!M13,Despiece!N13)<$Q$3,MAX(Despiece!M13,Despiece!N13)<$Q$4),"Pequeña","Normal")) -> Pequeña | M13: =Despiece!E13&" × "&Despiece!F13 -> 830 × 80 | N13: =IF(LEN(TRIM(IF($L13="Pequeña","Si no la cantean: cortar a "&ROUND(Despiece!M13,2)&" × "&ROUND(Despiece!N13,2)&" y cantear en el armado.","")&" "&IFERROR(VLOOKUP(Despiece!A13,$S$2:$T$40,2,FALSE),"")))=0,"—",TRIM(IF($L13="Pequeña","Si no la cantean: cortar a "&ROUND(Despiece!M13,2)&" × "&ROUND(Despiece!N13,2)&" y cantear en el armado.","")&" "&IFERROR(VLOOKUP(Despiece!A13,$S$2:$T$40,2,FALSE),""))) -> Si no la cantean: cortar a 830 × 79,55 y cantear en el armado.
A14: =Despiece!A14 -> C3-008 | B14: =Despiece!B14 -> B1 | C14: =Despiece!C14 -> Refuerzo trasero de maletero | D14: ="RH15 Cartagena "&Despiece!G14&" mm" -> RH15 Cartagena 15 mm | E14: =Despiece!D14 -> 1 | F14: =IF($Q$2="NO",ROUND(Despiece!M14,2),Despiece!E14) -> 830 | G14: =IF($Q$2="NO",ROUND(Despiece!N14,2),Despiece!F14) -> 100 | H14: =IF(Despiece!I14="2","R",IF(Despiece!I14="0.45","F","—")) -> F | I14: =IF(Despiece!J14="2","R",IF(Despiece!J14="0.45","F","—")) -> — | J14: =IF(Despiece!K14="2","R",IF(Despiece!K14="0.45","F","—")) -> — | K14: =IF(Despiece!L14="2","R",IF(Despiece!L14="0.45","F","—")) -> — | L14: =IF(SUMPRODUCT((Despiece!I14:L14="2")+(Despiece!I14:L14="0.45"))=0,"Sin canto",IF(OR(MIN(Despiece!M14,Despiece!N14)<$Q$3,MAX(Despiece!M14,Despiece!N14)<$Q$4),"Pequeña","Normal")) -> Pequeña | M14: =Despiece!E14&" × "&Despiece!F14 -> 830 × 100 | N14: =IF(LEN(TRIM(IF($L14="Pequeña","Si no la cantean: cortar a "&ROUND(Despiece!M14,2)&" × "&ROUND(Despiece!N14,2)&" y cantear en el armado.","")&" "&IFERROR(VLOOKUP(Despiece!A14,$S$2:$T$40,2,FALSE),"")))=0,"—",TRIM(IF($L14="Pequeña","Si no la cantean: cortar a "&ROUND(Despiece!M14,2)&" × "&ROUND(Despiece!N14,2)&" y cantear en el armado.","")&" "&IFERROR(VLOOKUP(Despiece!A14,$S$2:$T$40,2,FALSE),""))) -> Si no la cantean: cortar a 830 × 99,55 y cantear en el armado.
A15: =Despiece!A15 -> C3-009 | B15: =Despiece!B15 -> B2 | C15: =Despiece!C15 -> Piso sobre base | D15: ="RH15 Cartagena "&Despiece!G15&" mm" -> RH15 Cartagena 15 mm | E15: =Despiece!D15 -> 1 | F15: =IF($Q$2="NO",ROUND(Despiece!M15,2),Despiece!E15) -> 1075 | G15: =IF($Q$2="NO",ROUND(Despiece!N15,2),Despiece!F15) -> 560 | H15: =IF(Despiece!I15="2","R",IF(Despiece!I15="0.45","F","—")) -> R | I15: =IF(Despiece!J15="2","R",IF(Despiece!J15="0.45","F","—")) -> — | J15: =IF(Despiece!K15="2","R",IF(Despiece!K15="0.45","F","—")) -> F | K15: =IF(Despiece!L15="2","R",IF(Despiece!L15="0.45","F","—")) -> — | L15: =IF(SUMPRODUCT((Despiece!I15:L15="2")+(Despiece!I15:L15="0.45"))=0,"Sin canto",IF(OR(MIN(Despiece!M15,Despiece!N15)<$Q$3,MAX(Despiece!M15,Despiece!N15)<$Q$4),"Pequeña","Normal")) -> Normal | M15: =Despiece!E15&" × "&Despiece!F15 -> 1075 × 560 | N15: =IF(LEN(TRIM(IF($L15="Pequeña","Si no la cantean: cortar a "&ROUND(Despiece!M15,2)&" × "&ROUND(Despiece!N15,2)&" y cantear en el armado.","")&" "&IFERROR(VLOOKUP(Despiece!A15,$S$2:$T$40,2,FALSE),"")))=0,"—",TRIM(IF($L15="Pequeña","Si no la cantean: cortar a "&ROUND(Despiece!M15,2)&" × "&ROUND(Despiece!N15,2)&" y cantear en el armado.","")&" "&IFERROR(VLOOKUP(Despiece!A15,$S$2:$T$40,2,FALSE),""))) -> —
A16: =Despiece!A16 -> C3-010 | B16: =Despiece!B16 -> B2 | C16: =Despiece!C16 -> Tapa superior | D16: ="RH15 Cartagena "&Despiece!G16&" mm" -> RH15 Cartagena 15 mm | E16: =Despiece!D16 -> 1 | F16: =IF($Q$2="NO",ROUND(Despiece!M16,2),Despiece!E16) -> 1075 | G16: =IF($Q$2="NO",ROUND(Despiece!N16,2),Despiece!F16) -> 505 | H16: =IF(Despiece!I16="2","R",IF(Despiece!I16="0.45","F","—")) -> F | I16: =IF(Despiece!J16="2","R",IF(Despiece!J16="0.45","F","—")) -> — | J16: =IF(Despiece!K16="2","R",IF(Despiece!K16="0.45","F","—")) -> — | K16: =IF(Despiece!L16="2","R",IF(Despiece!L16="0.45","F","—")) -> — | L16: =IF(SUMPRODUCT((Despiece!I16:L16="2")+(Despiece!I16:L16="0.45"))=0,"Sin canto",IF(OR(MIN(Despiece!M16,Despiece!N16)<$Q$3,MAX(Despiece!M16,Despiece!N16)<$Q$4),"Pequeña","Normal")) -> Normal | M16: =Despiece!E16&" × "&Despiece!F16 -> 1075 × 505 | N16: =IF(LEN(TRIM(IF($L16="Pequeña","Si no la cantean: cortar a "&ROUND(Despiece!M16,2)&" × "&ROUND(Despiece!N16,2)&" y cantear en el armado.","")&" "&IFERROR(VLOOKUP(Despiece!A16,$S$2:$T$40,2,FALSE),"")))=0,"—",TRIM(IF($L16="Pequeña","Si no la cantean: cortar a "&ROUND(Despiece!M16,2)&" × "&ROUND(Despiece!N16,2)&" y cantear en el armado.","")&" "&IFERROR(VLOOKUP(Despiece!A16,$S$2:$T$40,2,FALSE),""))) -> —
A17: =Despiece!A17 -> C3-011 | B17: =Despiece!B17 -> B2 | C17: =Despiece!C17 -> Fondo RH15 | D17: ="RH15 Cartagena "&Despiece!G17&" mm" -> RH15 Cartagena 15 mm | E17: =Despiece!D17 -> 1 | F17: =IF($Q$2="NO",ROUND(Despiece!M17,2),Despiece!E17) -> 2250 | G17: =IF($Q$2="NO",ROUND(Despiece!N17,2),Despiece!F17) -> 1075 | H17: =IF(Despiece!I17="2","R",IF(Despiece!I17="0.45","F","—")) -> — | I17: =IF(Despiece!J17="2","R",IF(Despiece!J17="0.45","F","—")) -> — | J17: =IF(Despiece!K17="2","R",IF(Despiece!K17="0.45","F","—")) -> — | K17: =IF(Despiece!L17="2","R",IF(Despiece!L17="0.45","F","—")) -> — | L17: =IF(SUMPRODUCT((Despiece!I17:L17="2")+(Despiece!I17:L17="0.45"))=0,"Sin canto",IF(OR(MIN(Despiece!M17,Despiece!N17)<$Q$3,MAX(Despiece!M17,Despiece!N17)<$Q$4),"Pequeña","Normal")) -> Sin canto | M17: =Despiece!E17&" × "&Despiece!F17 -> 2250 × 1075 | N17: =IF(LEN(TRIM(IF($L17="Pequeña","Si no la cantean: cortar a "&ROUND(Despiece!M17,2)&" × "&ROUND(Despiece!N17,2)&" y cantear en el armado.","")&" "&IFERROR(VLOOKUP(Despiece!A17,$S$2:$T$40,2,FALSE),"")))=0,"—",TRIM(IF($L17="Pequeña","Si no la cantean: cortar a "&ROUND(Despiece!M17,2)&" × "&ROUND(Despiece!N17,2)&" y cantear en el armado.","")&" "&IFERROR(VLOOKUP(Despiece!A17,$S$2:$T$40,2,FALSE),""))) -> —
A18: =Despiece!A18 -> C3-012 | B18: =Despiece!B18 -> B2 | C18: =Despiece!C18 -> Piso de maletero | D18: ="RH15 Cartagena "&Despiece!G18&" mm" -> RH15 Cartagena 15 mm | E18: =Despiece!D18 -> 1 | F18: =IF($Q$2="NO",ROUND(Despiece!M18,2),Despiece!E18) -> 1075 | G18: =IF($Q$2="NO",ROUND(Despiece!N18,2),Despiece!F18) -> 475 | H18: =IF(Despiece!I18="2","R",IF(Despiece!I18="0.45","F","—")) -> R | I18: =IF(Despiece!J18="2","R",IF(Despiece!J18="0.45","F","—")) -> — | J18: =IF(Despiece!K18="2","R",IF(Despiece!K18="0.45","F","—")) -> — | K18: =IF(Despiece!L18="2","R",IF(Despiece!L18="0.45","F","—")) -> — | L18: =IF(SUMPRODUCT((Despiece!I18:L18="2")+(Despiece!I18:L18="0.45"))=0,"Sin canto",IF(OR(MIN(Despiece!M18,Despiece!N18)<$Q$3,MAX(Despiece!M18,Despiece!N18)<$Q$4),"Pequeña","Normal")) -> Normal | M18: =Despiece!E18&" × "&Despiece!F18 -> 1075 × 475 | N18: =IF(LEN(TRIM(IF($L18="Pequeña","Si no la cantean: cortar a "&ROUND(Despiece!M18,2)&" × "&ROUND(Despiece!N18,2)&" y cantear en el armado.","")&" "&IFERROR(VLOOKUP(Despiece!A18,$S$2:$T$40,2,FALSE),"")))=0,"—",TRIM(IF($L18="Pequeña","Si no la cantean: cortar a "&ROUND(Despiece!M18,2)&" × "&ROUND(Despiece!N18,2)&" y cantear en el armado.","")&" "&IFERROR(VLOOKUP(Despiece!A18,$S$2:$T$40,2,FALSE),""))) -> —
... A30: =Despiece!A30 -> C3-024 | B30: =Despiece!B30 -> EST | C30: =Despiece!C30 -> Solapa frontal | D30: ="RH15 Cartagena "&Despiece!G30&" mm" -> RH15 Cartagena 15 mm | E30: =Despiece!D30 -> 1 | F30: =IF($Q$2="NO",ROUND(Despiece!M30,2),Despiece!E30) -> 1950 | G30: =IF($Q$2="NO",ROUND(Despiece!N30,2),Despiece!F30) -> 120 | H30: =IF(Despiece!I30="2","R",IF(Despiece!I30="0.45","F","—")) -> R | I30: =IF(Despiece!J30="2","R",IF(Despiece!J30="0.45","F","—")) -> F | J30: =IF(Despiece!K30="2","R",IF(Despiece!K30="0.45","F","—")) -> R | K30: =IF(Despiece!L30="2","R",IF(Despiece!L30="0.45","F","—")) -> R | L30: =IF(SUMPRODUCT((Despiece!I30:L30="2")+(Despiece!I30:L30="0.45"))=0,"Sin canto",IF(OR(MIN(Despiece!M30,Despiece!N30)<$Q$3,MAX(Despiece!M30,Despiece!N30)<$Q$4),"Pequeña","Normal")) -> Normal | M30: =Despiece!E30&" × "&Despiece!F30 -> 1950 × 120 | N30: =IF(LEN(TRIM(IF($L30="Pequeña","Si no la cantean: cortar a "&ROUND(Despiece!M30,2)&" × "&ROUND(Despiece!N30,2)&" y cantear en el armado.","")&" "&IFERROR(VLOOKUP(Despiece!A30,$S$2:$T$40,2,FALSE),"")))=0,"—",TRIM(IF($L30="Pequeña","Si no la cantean: cortar a "&ROUND(Despiece!M30,2)&" × "&ROUND(Despiece!N30,2)&" y cantear en el armado.","")&" "&IFERROR(VLOOKUP(Despiece!A30,$S$2:$T$40,2,FALSE),""))) -> —
C32: Metros netos de canto | F32: Normal | G32: Pequeña
C33: Rígido 2 mm | F33: =(SUMPRODUCT(Despiece!$D$7:$D$30,Despiece!$E$7:$E$30,(Despiece!$I$7:$I$30="2")+(Despiece!$J$7:$J$30="2"),--($L$7:$L$30="Normal"))+SUMPRODUCT(Despiece!$D$7:$D$30,Despiece!$F$7:$F$30,(Despiece!$K$7:$K$30="2")+(Despiece!$L$7:$L$30="2"),--($L$7:$L$30="Normal")))/1000 -> 31.644 | G33: =(SUMPRODUCT(Despiece!$D$7:$D$30,Despiece!$E$7:$E$30,(Despiece!$I$7:$I$30="2")+(Despiece!$J$7:$J$30="2"),--($L$7:$L$30="Pequeña"))+SUMPRODUCT(Despiece!$D$7:$D$30,Despiece!$F$7:$F$30,(Despiece!$K$7:$K$30="2")+(Despiece!$L$7:$L$30="2"),--($L$7:$L$30="Pequeña")))/1000 -> 0
C34: Flexible 0,45 mm | F34: =(SUMPRODUCT(Despiece!$D$7:$D$30,Despiece!$E$7:$E$30,(Despiece!$I$7:$I$30="0.45")+(Despiece!$J$7:$J$30="0.45"),--($L$7:$L$30="Normal"))+SUMPRODUCT(Despiece!$D$7:$D$30,Despiece!$F$7:$F$30,(Despiece!$K$7:$K$30="0.45")+(Despiece!$L$7:$L$30="0.45"),--($L$7:$L$30="Normal")))/1000 -> 21.082 | G34: =(SUMPRODUCT(Despiece!$D$7:$D$30,Despiece!$E$7:$E$30,(Despiece!$I$7:$I$30="0.45")+(Despiece!$J$7:$J$30="0.45"),--($L$7:$L$30="Pequeña"))+SUMPRODUCT(Despiece!$D$7:$D$30,Despiece!$F$7:$F$30,(Despiece!$K$7:$K$30="0.45")+(Despiece!$L$7:$L$30="0.45"),--($L$7:$L$30="Pequeña")))/1000 -> 17.963
C35: Piezas (unidades) | F35: =SUMPRODUCT($E$7:$E$30,--($L$7:$L$30<>"Pequeña")) -> 32 | G35: =SUMIF($L$7:$L$30,"Pequeña",$E$7:$E$30) -> 12
C37: Canto para acabado manual · previsión sujeta a la entrega | F37: Rígido 2 mm | G37: Flexible 0,45 mm
C38: Bordes a cantear a mano | F38: =SUMPRODUCT(Despiece!$D$7:$D$30,(Despiece!$I$7:$I$30="2")+(Despiece!$J$7:$J$30="2")+(Despiece!$K$7:$K$30="2")+(Despiece!$L$7:$L$30="2"),--($L$7:$L$30="Pequeña")) -> 0 | G38: =SUMPRODUCT(Despiece!$D$7:$D$30,(Despiece!$I$7:$I$30="0.45")+(Despiece!$J$7:$J$30="0.45")+(Despiece!$K$7:$K$30="0.45")+(Despiece!$L$7:$L$30="0.45"),--($L$7:$L$30="Pequeña")) -> 33
C39: Metros netos | F39: =G33 -> 0 | G39: =G34 -> 17.963
C40: Desperdicio por borde a mano (m) | F40: 0.1 | G40: 0.1
C41: Margen de seguridad | F41: 0.2 | G41: 0.2
C42: Estimado con desperdicio y reserva (m) | F42: =IF(F38=0,0,ROUNDUP((F39+F38*F40)*(1+F41),0)) -> 0 | G42: =IF(G38=0,0,ROUNDUP((G39+G38*G40)*(1+G41),0)) -> 26
C43: Previsión para las piezas pequeñas, no garantía de cuáles canteará Madecentro. Incluye 10 cm extra por borde y 20 % de reserva; ambos valores son editables. Al recibir las piezas, ajustar el objetivo si faltan otros bordes o si el proveedor canteó parte de ellos.
C44: Objetivo revisado con reserva (m; opcional)
C45: Metros ya disponibles para cantear en casa | F45: 0 | G45: 0
C46: Metros faltantes por comprar | F46: =ROUNDUP(MAX(IF(ISNUMBER(F44),F44,F42)-F45,0),0) -> 0 | G46: =ROUNDUP(MAX(IF(ISNUMBER(G44),G44,G42)-G45,0),0) -> 26
C47: Dejar el objetivo revisado vacío para usar el estimado. Si ya hay canto comprado o sobrante de rollos, anotarlo en metros disponibles. No sumar este material dos veces al presupuesto. Precio por metro suelto y pegante por cotizar con el proveedor.

Sheet Compras
A2: Clóset compacto: compras independientes
A3: Presupuesto parcial del clóset principal. Precios de referencia; materiales independientes de la cocina.
A4: Cinco láminas es un encaje encontrado sin rotar por veta; no representa un mínimo demostrado.
A6: Referencia | B6: Uso | C6: Cantidad | D6: Unidad | E6: Precio COP | F6: Importe COP | G6: Estado | H6: Detalle | J6: Fuente / fecha
A7: RH15 Cartagena | B7: Tablero 2440 × 2150 | C7: 5 | D7: lámina | E7: 365872 | F7: =IF(COUNT(C7,E7)=2,C7*E7,"Por cotizar") -> 1829360 | G7: Misma referencia cocina | H7: 44 piezas RH15, más el listón de pino del bastidor (fila Pino). Encaje encontrado en 5 láminas, con sierra 4 mm y refilado 10 mm por lado. La presencia de fondos y hojas grandes aumenta consumo. Proveedor define plano final. | J7: despiece-cocina.xlsx, Compras; precio de referencia 27/10/2026.
A8: Canto rígido Cartagena | B8: Rollo 19 × 2 mm | C8: =Cantos!H7 -> 1 | D8: rollo | E8: 531600 | F8: =IF(COUNT(C8,E8)=2,C8*E8,"Por cotizar") -> 531600 | G8: Referencia cocina | H8: Cantidad exclusiva de este clóset, calculada en Cantos. No se han descontado sobrantes de otros muebles. Para acabado manual: ver «Metros faltantes por comprar» al final de Pedido de corte; descontar material ya disponible. Precio por metro suelto y pegante por cotizar. | J8: despiece-cocina.xlsx, Compras.
A9: Canto flexible Cartagena | B9: Rollo 19 × 0,45 mm | C9: =Cantos!H8 -> 1 | D9: rollo | E9: 285600 | F9: =IF(COUNT(C9,E9)=2,C9*E9,"Por cotizar") -> 285600 | G9: Referencia cocina | H9: Confirmar SKU, suministro y canteado de piezas estrechas. Con el criterio de bordes vistos, cocina y clóset juntos necesitan unos 90 m de canto flexible: caben en un solo rollo de 200 m si se compran juntos. Para acabado manual: ver «Metros faltantes por comprar» al final de Pedido de corte; descontar material ya disponible. Precio por metro suelto y pegante por cotizar. | J9: despiece-cocina.xlsx, Compras.
A10: HRE320-45 | B10: Riel lateral 450 mm | C10: 3 | D10: par | E10: 11287 | F10: =IF(COUNT(C10,E10)=2,C10*E10,"Por cotizar") -> 33861 | G10: Precio aportado | H10: Vano 830 − 27 = caja 803 × 450. Los 45 kg nominales del par no certifican la caja ni la carga útil. Incluye 12 tornillos de 12 mm por par. Confirmar uniones. | J10: Usuario; ficha HRE320/330 rev. 15/05/25.
A11: FSCPCM20 | B11: Kit Peralma para dos hojas | C11: 1 | D11: kit | E11: 12730 | F11: =IF(COUNT(C11,E11)=2,C11*E11,"Por cotizar") -> 12730 | G11: Candidato | H11: Kit publicado: 4 rodamientos, 1 guía, 1 tope y tornillos. Identificar si coinciden con la guía y el amortiguador descritos por el usuario, antes de añadir accesorios. Cada hoja RH pesa 21,3 kg sin herrajes (10,05 kg/m², dato de Madecentro); el kit indica 30 kg: preguntar si es por hoja o por kit de dos. | J11: https://madecentro.com/products/kit-de-accesorios-para-sistema-colgante; precio aportado por usuario.
A12: PERALMA50B · 2 m | B12: Riel colgante superior para 2 hojas | C12: 1 | D12: barra | E12: 33278 | F12: =IF(COUNT(C12,E12)=2,C12*E12,"Por cotizar") -> 33278 | G12: Precio aportado | H12: Barra 2 m para recorrido 1920 mm. Referencia real: zona de 70 mm de fondo, hojas entre 500 y 550 mm, cuerpo hasta 560. El riel se atornilla al listón de pino del bastidor (no a la tapa). Guía inferior sin apoyo de peso; no hay riel inferior de carga. Confirmar sección y taladros del sistema. | J12: https://madecentro.com/products/sistema-corredizo-colgate-x-3mtr
A13: HMA310-02 | B13: Manija tubular CC96 mm | C13: 2 | D13: unidad | E13: 2743 | F13: =IF(COUNT(C13,E13)=2,C13*E13,"Por cotizar") -> 5486 | G13: Elegida | H13: Una manija vertical en el extremo exterior de cada hoja.35 mm de saliente: fondo máximo 585 mm. Dos centros 96 mm; largo representado 119 mm. Las manijas no sustituyen una certificación de rigidez del tablero. | J13: Usuario: $2.743/unidad. https://madecentro.com/products/hma310-02-manija-310-acero-inox-cc-96-mm-rectangular-alta
A14: Verificar con FSCPCM20 | B14: Tope plástico amortiguado | D14: conjunto | F14: =IF(COUNT(C14,E14)=2,C14*E14,"Por cotizar") -> Por cotizar | G14: Verificar incluido | H14: Detrás de la hoja exterior, conserva 50 mm de desfase y evita invertir el orden de hojas. Cota de pérdida de recorrido aportada por el usuario. Verificar si viene en el kit; no duplicar compra. La guía inferior tampoco se compra dos veces. | J14: Descripción y fotos del clóset real del usuario; referencia comercial pendiente.
A15: Por elegir | B15: Barras para colgar | C15: 3 | D15: tramo | F15: =IF(COUNT(C15,E15)=2,C15*E15,"Por cotizar") -> Por cotizar | G15: Cotizar | H15: Una ilustrada 810 mm y dos 1055 mm. Barra baja derecha desmontable. Medidas de corte reales según soportes elegidos. | J15: Modelo; no representa una referencia comercial confirmada.
A16: Por elegir | B16: Soportes de barra | C16: 6 | D16: unidad | F16: =IF(COUNT(C16,E16)=2,C16*E16,"Por cotizar") -> Por cotizar | G16: Cotizar | H16: Dos por barra. Fijación y carga para RH15 por confirmar. | J16: Montaje pendiente.
A17: Por dimensionar | B17: Apoyos de base | C17: 6 | D17: unidad | F17: =IF(COUNT(C17,E17)=2,C17*E17,"Por cotizar") -> Por cotizar | G17: Cotizar | H17: Dos bajo cada lateral/divisor. El modelo dibuja 20 mm de apoyo y base total 100 mm; producto y regulación por elegir. | J17: Geometría propuesta.
A18: Por dimensionar | B18: Uniones y anclajes | C18: 1 | D18: lote | F18: =IF(COUNT(C18,E18)=2,C18*E18,"Por cotizar") -> Por cotizar | G18: Cotizar | H18: Incluye fijación de fondos, estructura y refuerzos de RH; el bastidor del riel se lista aparte. El extremo derecho queda libre: no puede anclarse al muro lateral derecho. Definir anclaje posterior y lateral izquierdo según muro. | J18: Montaje y sustrato real.
A19: Pino · por cotizar | B19: Listón 4×4 cm · bastidor del riel | C19: 1 | D19: listón | F19: =IF(COUNT(C19,E19)=2,C19*E19,"Por cotizar") -> Por cotizar | G19: Cotizar | H19: Listón de pino de 4×4 cm que va de lateral a lateral: 1920 mm libres más el encaje en cada lateral (máx. 7 mm por lado). Pedir de 2,0 m o más, recto, seco y sin nudos grandes; sobra para 2 tacos de 15 mm. Va encajonado y atornillado a los laterales; el riel (50 mm) se atornilla a su cara inferior y sobresale ~5 mm por lado. El clóset real usa 7×3 cm; se cambió a 4×4 por disponibilidad. Confirmar rebaje y tornillos con el instalador. | J19: Descripción del clóset real del usuario, 27/10/2026; precio pendiente.
A20: Por elegir | B20: Tornillos del bastidor y del riel | C20: 1 | D20: lote | F20: =IF(COUNT(C20,E20)=2,C20*E20,"Por cotizar") -> Por cotizar | G20: Cotizar | H20: Tornillos para madera y aglomerado en cada extremo del listón y para el riel; el kit del sistema puede traer los suyos. Escuadras solo si el rebaje en los laterales queda corto. | J20: Montaje pendiente.
A21: Por cotizar | B21: Corte, canteado e instalación | C21: 1 | D21: servicio | F21: =IF(COUNT(C21,E21)=2,C21*E21,"Por cotizar") -> Por cotizar | G21: Cotizar | H21: Confirmar plantilla de las hojas y perfiles, guías y topes adicionales, veta y suministro. Mantener todo este presupuesto independiente. | J21: Proveedor.
A22: SUBTOTAL PARCIAL | F22: =SUM(F7:F21) -> 2731915 | H22: Incluye 2 manijas por $5.486. Quedan listón de pino, tornillos, barras, apoyos, uniones, anclajes y servicios. Verificar accesorios incluidos. No hay PERALM93 presupuestado en este diseño.

Sheet Cantos
A2: Clóset compacto: cantos exclusivos | H2: Reserva/borde m | I2: 0.05
A3: Rígido 2 mm en caras vistas; flexible 0,45 en bordes vistos interiores, superiores e inferiores. Sin canto en bordes ocultos contra otra pieza o el muro. Reserva editable, 5 cm por borde.
A6: Tipo | B6: Aplicación | C6: Metros netos | D6: Bordes | E6: Reserva m | F6: Metros a pedir | G6: m por rollo | H6: Rollos
A7: Rígido 19 × 2 | B7: Hojas, frentes y bordes vistos de estructura | C7: =SUMPRODUCT(Despiece!$D$7:$D$30,Despiece!$E$7:$E$30,(Despiece!$I$7:$I$30="2")+(Despiece!$J$7:$J$30="2"))/1000+SUMPRODUCT(Despiece!$D$7:$D$30,Despiece!$F$7:$F$30,(Despiece!$K$7:$K$30="2")+(Despiece!$L$7:$L$30="2"))/1000 -> 31.644 | D7: =SUMPRODUCT(Despiece!$D$7:$D$30,(Despiece!$I$7:$I$30="2")+(Despiece!$J$7:$J$30="2")+(Despiece!$K$7:$K$30="2")+(Despiece!$L$7:$L$30="2")) -> 30 | E7: =D7*$I$2 -> 1.5 | F7: =ROUNDUP((C7+E7)/5,0)*5 -> 35 | G7: 100 | H7: =ROUNDUP(F7/G7,0) -> 1
A8: Flexible 19 × 0,45 | B8: Bordes vistos interiores, superiores e inferiores, y base | C8: =SUMPRODUCT(Despiece!$D$7:$D$30,Despiece!$E$7:$E$30,(Despiece!$I$7:$I$30="0.45")+(Despiece!$J$7:$J$30="0.45"))/1000+SUMPRODUCT(Despiece!$D$7:$D$30,Despiece!$F$7:$F$30,(Despiece!$K$7:$K$30="0.45")+(Despiece!$L$7:$L$30="0.45"))/1000 -> 39.045 | D8: =SUMPRODUCT(Despiece!$D$7:$D$30,(Despiece!$I$7:$I$30="0.45")+(Despiece!$J$7:$J$30="0.45")+(Despiece!$K$7:$K$30="0.45")+(Despiece!$L$7:$L$30="0.45")) -> 70 | E8: =D8*$I$2 -> 3.5 | F8: =ROUNDUP((C8+E8)/5,0)*5 -> 45 | G8: 200 | H8: =ROUNDUP(F8/G8,0) -> 1
A10: Piezas estrechas: la base (C3-020 a C3-022) conserva canto en los 4 bordes por estar junto al piso; las demás llevan canto solo en bordes vistos. Confirmar preparación de uniones con el taller.

Sheet Pendientes
A2: Pendientes antes de cortar y armar · clóset principal 195
A3: Solo lo que falta resolver. Lo ya decidido está en la hoja Decisiones; el despiece y el 3D ya lo reflejan.
A6: N° | B6: Tema | C6: Qué falta | D6: Qué bloquea | E6: Quién lo define
A7: 1 | B7: Posición del eje de la puerta | C7: Confirmar en obra que el eje de la puerta de la habitación está a 2880 mm del muro izquierdo: el ancho de 1950 depende de esa cota (2880 − 900 − 10 − 20). | D7: Todo el corte | E7: Medición en obra
A8: 2 | B8: Proveedor de corte | C8: Confirmar Q2–Q4 del Pedido de corte (medida terminada y tamaño mínimo que cantea). Encaje previsto en 5 láminas. | D8: Pedido de corte | E8: Sucursal Madecentro
A9: 3 | B9: Hojas y sistema corredizo | C9: Confirmar con el kit Peralma FSCPCM20 la altura de hoja, la plantilla y la carga (hojas de ≈21,3 kg; el kit indica 30 kg: ¿por hoja o por kit?). Verificar si el tope amortiguado viene en el kit. | D9: No cortar C3-023 | E9: Proveedor del sistema
A10: 4 | B10: Bastidor del riel | C10: Rebaje en los laterales para el listón de pino 4 × 4 (máx. ≈7 mm), tornillos y tacos de la solapa. Revisar en obra si el listón baja con 43 kg; si baja, añadir un apoyo sobre el divisor. | D10: Rebaje de C3-001 en taller | E10: Instalador
A11: 5 | B11: Cajones | C11: Confirmar la fijación de las cajas y la carga útil con los rieles HRE320-45 (caja 803 × 450). | D11: Armado | E11: Ficha HRE320
A12: 6 | B12: Anclajes | C12: Anclaje al muro posterior e izquierdo; el extremo derecho queda libre. Definir tornillería y uniones de los fondos. | D12: Instalación | E12: Instalador
A13: 7 | B13: Montaje en altura | C13: Altura 2380 en hueco de 2400 (diagonal ≈2445): armar de pie o por partes; la nivelación consume los 20 mm superiores. | D13: Armado | E13: Taller
A14: 8 | B14: Accesorios | C14: Ajustar el tope (50 mm de desfase) y las manijas CC96 a los accesorios reales; taladros en obra. Elegir barras, soportes y apoyos de base. | D14: Compras y armado | E14: Usuario / instalador

Sheet Decisiones
A2: Decisiones aplicadas · clóset principal 195
A3: Registro de lo ya resuelto; el despiece y el 3D ya lo reflejan.
A6: Tema | B6: Decisión | C6: Fecha / fuente
A7: Puerta de habitación | B7: Hoja 900 mm; eje a 520 mm del muro donde apoya el fondo del clóset. | C7: Confirmación del usuario 27/10/2026.
A8: Ancho propuesto | B8: El modelo sitúa el eje a 2880 mm del muro izquierdo. Extremo del giro=2880−900=1980. Restando 10 mm de separación izquierda y 20 mm de margen: ancho 1950 mm. Confirmar posición lateral del eje antes de fabricar. | C8: Geometría de la terraza y medidas confirmadas.
A9: Ubicación y franja libre | B9: 1+195+94=290 cm. Se reduce 93 cm respecto a 288. El hueco derecho es reserva de giro; no un paso peatonal libre de 94 cm. | C9: Cálculo de ubicación.
A10: Fondo interior | B10: Zona de referencia 490–560 mm. Hoja interior 500–515; exterior 535–550. Cuerpo 560 y manijas hasta 585. Fondo RH15 de 0–15 deja 485 mm útiles. Los 7 cm son la zona de referencia del marco, no un espesor adicional del cuerpo. | C10: Medidas y aclaraciones del usuario / modelo.
A11: Distribución | B11: Útiles 830 y 1075 mm. Se redujo el cajonero de 880 a 830 mm para sumar 50 mm de tolerancia de instalación, además del descuento ya aplicado por el tope. Se mantienen 1950 mm exteriores. Colgado corto arriba, doble colgado derecho con barra inferior desmontable y maleteros interiores. | C11: Geometría del diseño.
A12: Acceso a cajones | B12: Hoja exterior izquierda e interior derecha; anchos 975, solape 30 y desfase mínimo 50. Desplazamiento y abertura libre 895. Frentes 824 en cuerpo 830: máximo x 842, hoja apilada comienza en x 910, dejando 68 mm de margen al tablero. Incluso con 50 mm adicionales de pérdida de recorrido quedaría un margen geométrico de 18 mm. El visor bloquea cruce de hojas y cajones tapados. | C12: Tope descrito por el usuario y control geométrico.
A13: Cajas y correderas | B13: Exterior 803×450; base RH15 aplicada, paredes 155 y refuerzo 40 inferior. Frente 824×210. Tres frentes con 30 mm de separación, sin manijas.803=830−27 de la familia HRE320. Confirmar fijación y carga útil. | C13: Geometría y ficha de rieles.
A14: Material y alcance | B14: Misma referencia RH15 Cartagena que la cocina final. Despiece y compras exclusivos del clóset compacto; no se han fusionado con cocina ni baño. | C14: Solicitud del usuario y Excel de cocina.
A15: Cantos | B15: Se retira el canto de los bordes ocultos contra otra pieza o el muro (fondos RH15 sin canto). Se conservan bordes vistos, el superior de laterales y divisor, y los 4 bordes de la base (C3-020 a C3-022). Cortes M/N pasan a fórmula según los cantos. Flexible 89,4 → 39,0 m netos; rígido sin cambio. | C15: Análisis geométrico del modelo 3D y decisión del usuario 27/10/2026.
